[
  {
    "PlayerId": 90036291,
    "FirstName": "Mahmoud Ahmed Ibrahim",
    "LastName": "Hassan",
    "CommonName": "Trezeguet",
    "ShortName": "Trezeguet",
    "Position": "M",
    "PositionCategory": "M",
    "Jersey": 7,
    "Foot": "Both",
    "Height": 181,
    "Weight": 77,
    "Gender": "Male",
    "BirthDate": "1994-01-10T00:00:00",
    "BirthCity": "Kafr al-Šayḫ",
    "BirthCountry": "Egypt",
    "Nationality": "Egypt",
    "InjuryStatus": "Scrambled",
    "InjuryBodyPart": "Scrambled",
    "InjuryNotes": "Scrambled",
    "InjuryStartDate": null,
    "Updated": "2025-07-04T04:38:09",
    "PhotoUrl": "https://s3-us-west-2.amazonaws.com/static.fantasydata.com/headshots/soc/low-res/90036291.png",
    "RotoWirePlayerID": null,
    "DraftKingsPosition": "M",
    "UsaTodayPlayerID": null,
    "UsaTodayHeadshotUrl": null,
    "UsaTodayHeadshotNoBackgroundUrl": null,
    "UsaTodayHeadshotUpdated": null,
    "UsaTodayHeadshotNoBackgroundUpdated": null
  },
  {
    "PlayerId": 90046493,
    "FirstName": "Achraf",
    "LastName": "Bencharki",
    "CommonName": "Achraf Bencharki",
    "ShortName": "A. Bencharki",
    "Position": "M",
    "PositionCategory": "M",
    "Jersey": 17,
    "Foot": "Right",
    "Height": 176,
    "Weight": 76,
    "Gender": "Male",
    "BirthDate": "1994-09-24T00:00:00",
    "BirthCity": "Oulad Zbair",
    "BirthCountry": "Morocco",
    "Nationality": "Morocco",
    "InjuryStatus": "Scrambled",
    "InjuryBodyPart": "Scrambled",
    "InjuryNotes": "Scrambled",
    "InjuryStartDate": null,
    "Updated": "2025-07-04T07:57:15",
    "PhotoUrl": "https://s3-us-west-2.amazonaws.com/static.fantasydata.com/headshots/soc/low-res/90046493.png",
    "RotoWirePlayerID": null,
    "DraftKingsPosition": null,
    "UsaTodayPlayerID": null,
    "UsaTodayHeadshotUrl": null,
    "UsaTodayHeadshotNoBackgroundUrl": null,
    "UsaTodayHeadshotUpdated": null,
    "UsaTodayHeadshotNoBackgroundUpdated": null
  },
  {
    "PlayerId": 90048361,
    "FirstName": "Hussein Ali El Shahat Ali",
    "LastName": "Hassan",
    "CommonName": "Hussein El Shahat",
    "ShortName": "Hussein El Shahat",
    "Position": "M",
    "PositionCategory": "M",
    "Jersey": 14,
    "Foot": "Right",
    "Height": 171,
    "Weight": 68,
    "Gender": "Male",
    "BirthDate": "1992-06-21T00:00:00",
    "BirthCity": "Cairo",
    "BirthCountry": "Egypt",
    "Nationality": "Egypt",
    "InjuryStatus": "Scrambled",
    "InjuryBodyPart": "Scrambled",
    "InjuryNotes": "Scrambled",
    "InjuryStartDate": null,
    "Updated": "2025-07-04T08:26:16",
    "PhotoUrl": "https://s3-us-west-2.amazonaws.com/static.fantasydata.com/headshots/soc/low-res/90048361.png",
    "RotoWirePlayerID": null,
    "DraftKingsPosition": null,
    "UsaTodayPlayerID": null,
    "UsaTodayHeadshotUrl": null,
    "UsaTodayHeadshotNoBackgroundUrl": null,
    "UsaTodayHeadshotUpdated": null,
    "UsaTodayHeadshotNoBackgroundUpdated": null
  },
  {
    "PlayerId": 90061580,
    "FirstName": "Mohamed Elsayed Mohamed",
    "LastName": "El Shenawy",
    "CommonName": "Mohamed El Shenawy",
    "ShortName": "Mohamed El Shenawy",
    "Position": "GK",
    "PositionCategory": "GK",
    "Jersey": 1,
    "Foot": "Right",
    "Height": 191,
    "Weight": 86,
    "Gender": "Male",
    "BirthDate": "1988-12-18T00:00:00",
    "BirthCity": "El Hamool",
    "BirthCountry": "Egypt",
    "Nationality": "Egypt",
    "InjuryStatus": "Scrambled",
    "InjuryBodyPart": "Scrambled",
    "InjuryNotes": "Scrambled",
    "InjuryStartDate": null,
    "Updated": "2025-06-17T06:45:23",
    "PhotoUrl": "https://s3-us-west-2.amazonaws.com/static.fantasydata.com/headshots/soc/low-res/90061580.png",
    "RotoWirePlayerID": null,
    "DraftKingsPosition": "GK",
    "UsaTodayPlayerID": null,
    "UsaTodayHeadshotUrl": null,
    "UsaTodayHeadshotNoBackgroundUrl": null,
    "UsaTodayHeadshotUpdated": null,
    "UsaTodayHeadshotNoBackgroundUpdated": null
  },
  {
    "PlayerId": 90061581,
    "FirstName": "Mohamed Magdy Mohamed",
    "LastName": "Moursy",
    "CommonName": "Afsha",
    "ShortName": "Afsha",
    "Position": "M",
    "PositionCategory": "M",
    "Jersey": 19,
    "Foot": "Right",
    "Height": 168,
    "Weight": null,
    "Gender": "Male",
    "BirthDate": "1996-03-06T00:00:00",
    "BirthCity": null,
    "BirthCountry": "Egypt",
    "Nationality": "Egypt",
    "InjuryStatus": "Scrambled",
    "InjuryBodyPart": "Scrambled",
    "InjuryNotes": "Scrambled",
    "InjuryStartDate": null,
    "Updated": "2025-06-14T19:08:38",
    "PhotoUrl": "https://s3-us-west-2.amazonaws.com/static.fantasydata.com/headshots/soc/low-res/90061581.png",
    "RotoWirePlayerID": null,
    "DraftKingsPosition": null,
    "UsaTodayPlayerID": null,
    "UsaTodayHeadshotUrl": null,
    "UsaTodayHeadshotNoBackgroundUrl": null,
    "UsaTodayHeadshotUpdated": null,
    "UsaTodayHeadshotNoBackgroundUpdated": null
  },
  {
    "PlayerId": 90069247,
    "FirstName": "Mohamed Hany Gamal",
    "LastName": "El Demerdash",
    "CommonName": "Mohamed Hany",
    "ShortName": "Mohamed Hany",
    "Position": "D",
    "PositionCategory": "D",
    "Jersey": 30,
    "Foot": "Right",
    "Height": 175,
    "Weight": null,
    "Gender": "Male",
    "BirthDate": "1996-02-02T00:00:00",
    "BirthCity": "Cairo",
    "BirthCountry": "Egypt",
    "Nationality": "Egypt",
    "InjuryStatus": "Scrambled",
    "InjuryBodyPart": "Scrambled",
    "InjuryNotes": "Scrambled",
    "InjuryStartDate": null,
    "Updated": "2025-06-14T19:08:38",
    "PhotoUrl": "https://s3-us-west-2.amazonaws.com/static.fantasydata.com/headshots/soc/low-res/90069247.png",
    "RotoWirePlayerID": null,
    "DraftKingsPosition": null,
    "UsaTodayPlayerID": null,
    "UsaTodayHeadshotUrl": null,
    "UsaTodayHeadshotNoBackgroundUrl": null,
    "UsaTodayHeadshotUpdated": null,
    "UsaTodayHeadshotNoBackgroundUpdated": null
  },
  {
    "PlayerId": 90070293,
    "FirstName": "Achraf",
    "LastName": "Dari",
    "CommonName": "Achraf Dari",
    "ShortName": "A. Dari",
    "Position": "D",
    "PositionCategory": "D",
    "Jersey": 15,
    "Foot": "Right",
    "Height": 188,
    "Weight": null,
    "Gender": "Male",
    "BirthDate": "1999-05-06T00:00:00",
    "BirthCity": null,
    "BirthCountry": "Morocco",
    "Nationality": "Morocco",
    "InjuryStatus": "Scrambled",
    "InjuryBodyPart": "Scrambled",
    "InjuryNotes": "Scrambled",
    "InjuryStartDate": null,
    "Updated": "2025-06-14T19:08:38",
    "PhotoUrl": "https://s3-us-west-2.amazonaws.com/static.fantasydata.com/headshots/soc/low-res/90070293.png",
    "RotoWirePlayerID": null,
    "DraftKingsPosition": "D",
    "UsaTodayPlayerID": null,
    "UsaTodayHeadshotUrl": null,
    "UsaTodayHeadshotNoBackgroundUrl": null,
    "UsaTodayHeadshotUpdated": null,
    "UsaTodayHeadshotNoBackgroundUpdated": null
  },
  {
    "PlayerId": 90070767,
    "FirstName": "Taher Mohamed Ahmed Taher Mohamed",
    "LastName": "Mahmoud",
    "CommonName": "Taher Mohamed",
    "ShortName": "Taher Mohamed",
    "Position": "A",
    "PositionCategory": "A",
    "Jersey": 29,
    "Foot": "Right",
    "Height": 186,
    "Weight": 79,
    "Gender": "Male",
    "BirthDate": "1997-03-07T00:00:00",
    "BirthCity": "Cairo",
    "BirthCountry": "Egypt",
    "Nationality": "Egypt",
    "InjuryStatus": "Scrambled",
    "InjuryBodyPart": "Scrambled",
    "InjuryNotes": "Scrambled",
    "InjuryStartDate": null,
    "Updated": "2025-06-14T19:08:38",
    "PhotoUrl": "https://s3-us-west-2.amazonaws.com/static.fantasydata.com/headshots/soc/low-res/0.png",
    "RotoWirePlayerID": null,
    "DraftKingsPosition": null,
    "UsaTodayPlayerID": null,
    "UsaTodayHeadshotUrl": null,
    "UsaTodayHeadshotNoBackgroundUrl": null,
    "UsaTodayHeadshotUpdated": null,
    "UsaTodayHeadshotNoBackgroundUpdated": null
  },
  {
    "PlayerId": 90083509,
    "FirstName": "Hamdy Fathy Abdelhalim",
    "LastName": "Abdelfattah",
    "CommonName": "Hamdy Fathy",
    "ShortName": "Hamdy Fathy",
    "Position": "M",
    "PositionCategory": "M",
    "Jersey": 8,
    "Foot": "Right",
    "Height": 180,
    "Weight": null,
    "Gender": "Male",
    "BirthDate": "1994-09-29T00:00:00",
    "BirthCity": null,
    "BirthCountry": "Egypt",
    "Nationality": "Egypt",
    "InjuryStatus": "Scrambled",
    "InjuryBodyPart": "Scrambled",
    "InjuryNotes": "Scrambled",
    "InjuryStartDate": null,
    "Updated": "2025-06-14T19:08:38",
    "PhotoUrl": "https://s3-us-west-2.amazonaws.com/static.fantasydata.com/headshots/soc/low-res/90083509.png",
    "RotoWirePlayerID": null,
    "DraftKingsPosition": null,
    "UsaTodayPlayerID": null,
    "UsaTodayHeadshotUrl": null,
    "UsaTodayHeadshotNoBackgroundUrl": null,
    "UsaTodayHeadshotUpdated": null,
    "UsaTodayHeadshotNoBackgroundUpdated": null
  },
  {
    "PlayerId": 90083786,
    "FirstName": "Ahmed Mostafa Mohamed",
    "LastName": "Sayed",
    "CommonName": "Zizo",
    "ShortName": "Zizo",
    "Position": "M",
    "PositionCategory": "M",
    "Jersey": 25,
    "Foot": "Right",
    "Height": 180,
    "Weight": 67,
    "Gender": "Male",
    "BirthDate": "1996-01-10T00:00:00",
    "BirthCity": null,
    "BirthCountry": "Egypt",
    "Nationality": "Egypt",
    "InjuryStatus": "Scrambled",
    "InjuryBodyPart": "Scrambled",
    "InjuryNotes": "Scrambled",
    "InjuryStartDate": null,
    "Updated": "2025-06-20T16:08:19",
    "PhotoUrl": "https://s3-us-west-2.amazonaws.com/static.fantasydata.com/headshots/soc/low-res/90083786.png",
    "RotoWirePlayerID": null,
    "DraftKingsPosition": null,
    "UsaTodayPlayerID": null,
    "UsaTodayHeadshotUrl": null,
    "UsaTodayHeadshotNoBackgroundUrl": null,
    "UsaTodayHeadshotUpdated": null,
    "UsaTodayHeadshotNoBackgroundUpdated": null
  },
  {
    "PlayerId": 90084118,
    "FirstName": "Mohamed Ali",
    "LastName": "Ben Romdhane",
    "CommonName": "Mohamed Ali Ben Romdhane",
    "ShortName": "M. Ben Romdhane",
    "Position": "M",
    "PositionCategory": "M",
    "Jersey": 5,
    "Foot": null,
    "Height": 185,
    "Weight": 77,
    "Gender": "Male",
    "BirthDate": "1999-09-06T00:00:00",
    "BirthCity": null,
    "BirthCountry": "Tunisia",
    "Nationality": "Tunisia",
    "InjuryStatus": "Scrambled",
    "InjuryBodyPart": "Scrambled",
    "InjuryNotes": "Scrambled",
    "InjuryStartDate": null,
    "Updated": "2025-06-14T19:08:38",
    "PhotoUrl": "https://s3-us-west-2.amazonaws.com/static.fantasydata.com/headshots/soc/low-res/90084118.png",
    "RotoWirePlayerID": null,
    "DraftKingsPosition": "M",
    "UsaTodayPlayerID": null,
    "UsaTodayHeadshotUrl": null,
    "UsaTodayHeadshotNoBackgroundUrl": null,
    "UsaTodayHeadshotUpdated": null,
    "UsaTodayHeadshotNoBackgroundUpdated": null
  },
  {
    "PlayerId": 90090828,
    "FirstName": "Aliou",
    "LastName": "Dieng",
    "CommonName": "Aliou Dieng",
    "ShortName": "A. Dieng",
    "Position": "M",
    "PositionCategory": "M",
    "Jersey": 23,
    "Foot": null,
    "Height": null,
    "Weight": null,
    "Gender": "Male",
    "BirthDate": "1997-10-16T00:00:00",
    "BirthCity": null,
    "BirthCountry": "Mali",
    "Nationality": "Mali",
    "InjuryStatus": "Scrambled",
    "InjuryBodyPart": "Scrambled",
    "InjuryNotes": "Scrambled",
    "InjuryStartDate": null,
    "Updated": "2025-06-14T19:08:38",
    "PhotoUrl": "https://s3-us-west-2.amazonaws.com/static.fantasydata.com/headshots/soc/low-res/0.png",
    "RotoWirePlayerID": null,
    "DraftKingsPosition": null,
    "UsaTodayPlayerID": null,
    "UsaTodayHeadshotUrl": null,
    "UsaTodayHeadshotNoBackgroundUrl": null,
    "UsaTodayHeadshotUpdated": null,
    "UsaTodayHeadshotNoBackgroundUpdated": null
  },
  {
    "PlayerId": 90091140,
    "FirstName": "Mohamed Sherif Mohamed Ragaei",
    "LastName": "Bakr",
    "CommonName": "Mohamed Sherif",
    "ShortName": "Mohamed Sherif",
    "Position": "A",
    "PositionCategory": "A",
    "Jersey": 9,
    "Foot": "Both",
    "Height": 184,
    "Weight": null,
    "Gender": "Male",
    "BirthDate": "1996-02-04T00:00:00",
    "BirthCity": null,
    "BirthCountry": "Egypt",
    "Nationality": "Egypt",
    "InjuryStatus": "Scrambled",
    "InjuryBodyPart": "Scrambled",
    "InjuryNotes": "Scrambled",
    "InjuryStartDate": null,
    "Updated": "2025-07-02T18:15:30",
    "PhotoUrl": "https://s3-us-west-2.amazonaws.com/static.fantasydata.com/headshots/soc/low-res/90091140.png",
    "RotoWirePlayerID": null,
    "DraftKingsPosition": null,
    "UsaTodayPlayerID": null,
    "UsaTodayHeadshotUrl": null,
    "UsaTodayHeadshotNoBackgroundUrl": null,
    "UsaTodayHeadshotUpdated": null,
    "UsaTodayHeadshotNoBackgroundUpdated": null
  },
  {
    "PlayerId": 90092410,
    "FirstName": "Reda",
    "LastName": "Slim",
    "CommonName": "Reda Slim",
    "ShortName": "R. Slim",
    "Position": "M",
    "PositionCategory": "M",
    "Jersey": null,
    "Foot": "Right",
    "Height": 176,
    "Weight": 64,
    "Gender": "Male",
    "BirthDate": "1999-10-05T00:00:00",
    "BirthCity": null,
    "BirthCountry": "Morocco",
    "Nationality": "Morocco",
    "InjuryStatus": "Scrambled",
    "InjuryBodyPart": "Scrambled",
    "InjuryNotes": "Scrambled",
    "InjuryStartDate": null,
    "Updated": "2025-04-17T09:25:05",
    "PhotoUrl": "https://s3-us-west-2.amazonaws.com/static.fantasydata.com/headshots/soc/low-res/90092410.png",
    "RotoWirePlayerID": null,
    "DraftKingsPosition": null,
    "UsaTodayPlayerID": null,
    "UsaTodayHeadshotUrl": null,
    "UsaTodayHeadshotNoBackgroundUrl": null,
    "UsaTodayHeadshotUpdated": null,
    "UsaTodayHeadshotNoBackgroundUpdated": null
  },
  {
    "PlayerId": 90094748,
    "FirstName": "Yasser Ahmed Ibrahim",
    "LastName": "El Hanafi",
    "CommonName": "Yasser Ibrahim",
    "ShortName": "Yasser Ibrahim",
    "Position": "D",
    "PositionCategory": "D",
    "Jersey": 6,
    "Foot": "Right",
    "Height": null,
    "Weight": null,
    "Gender": "Male",
    "BirthDate": "1993-02-10T00:00:00",
    "BirthCity": null,
    "BirthCountry": "Egypt",
    "Nationality": "Egypt",
    "InjuryStatus": "Scrambled",
    "InjuryBodyPart": "Scrambled",
    "InjuryNotes": "Scrambled",
    "InjuryStartDate": null,
    "Updated": "2025-06-14T19:08:38",
    "PhotoUrl": "https://s3-us-west-2.amazonaws.com/static.fantasydata.com/headshots/soc/low-res/0.png",
    "RotoWirePlayerID": null,
    "DraftKingsPosition": null,
    "UsaTodayPlayerID": null,
    "UsaTodayHeadshotUrl": null,
    "UsaTodayHeadshotNoBackgroundUrl": null,
    "UsaTodayHeadshotUpdated": null,
    "UsaTodayHeadshotNoBackgroundUpdated": null
  },
  {
    "PlayerId": 90099747,
    "FirstName": "Emam Ashour Metwaly",
    "LastName": "Abdelghany",
    "CommonName": "Emam Ashour",
    "ShortName": "Emam Ashour",
    "Position": "M",
    "PositionCategory": "M",
    "Jersey": 22,
    "Foot": "Right",
    "Height": 182,
    "Weight": null,
    "Gender": "Male",
    "BirthDate": "1998-02-20T00:00:00",
    "BirthCity": null,
    "BirthCountry": "Egypt",
    "Nationality": "Egypt",
    "InjuryStatus": "Scrambled",
    "InjuryBodyPart": "Scrambled",
    "InjuryNotes": "Scrambled",
    "InjuryStartDate": null,
    "Updated": "2025-06-14T19:08:38",
    "PhotoUrl": "https://s3-us-west-2.amazonaws.com/static.fantasydata.com/headshots/soc/low-res/0.png",
    "RotoWirePlayerID": null,
    "DraftKingsPosition": "M",
    "UsaTodayPlayerID": null,
    "UsaTodayHeadshotUrl": null,
    "UsaTodayHeadshotNoBackgroundUrl": null,
    "UsaTodayHeadshotUpdated": null,
    "UsaTodayHeadshotNoBackgroundUpdated": null
  },
  {
    "PlayerId": 90100017,
    "FirstName": "Omar Kamal Sayed",
    "LastName": "Abdelwahed",
    "CommonName": "Omar Kamal",
    "ShortName": "Omar Kamal",
    "Position": "M",
    "PositionCategory": "M",
    "Jersey": 3,
    "Foot": "Right",
    "Height": 186,
    "Weight": null,
    "Gender": "Male",
    "BirthDate": "1993-09-29T00:00:00",
    "BirthCity": null,
    "BirthCountry": "Egypt",
    "Nationality": "Egypt",
    "InjuryStatus": "Scrambled",
    "InjuryBodyPart": "Scrambled",
    "InjuryNotes": "Scrambled",
    "InjuryStartDate": null,
    "Updated": "2025-06-14T19:08:38",
    "PhotoUrl": "https://s3-us-west-2.amazonaws.com/static.fantasydata.com/headshots/soc/low-res/90100017.png",
    "RotoWirePlayerID": null,
    "DraftKingsPosition": null,
    "UsaTodayPlayerID": null,
    "UsaTodayHeadshotUrl": null,
    "UsaTodayHeadshotNoBackgroundUrl": null,
    "UsaTodayHeadshotUpdated": null,
    "UsaTodayHeadshotNoBackgroundUpdated": null
  },
  {
    "PlayerId": 90106516,
    "FirstName": "Karim Fouad Abdelhamid",
    "LastName": "Mahmoud",
    "CommonName": "Karim Fouad",
    "ShortName": "Karim Fouad",
    "Position": "D",
    "PositionCategory": "D",
    "Jersey": null,
    "Foot": "Both",
    "Height": 174,
    "Weight": null,
    "Gender": "Male",
    "BirthDate": "1999-10-01T00:00:00",
    "BirthCity": null,
    "BirthCountry": "Egypt",
    "Nationality": "Egypt",
    "InjuryStatus": "Scrambled",
    "InjuryBodyPart": "Scrambled",
    "InjuryNotes": "Scrambled",
    "InjuryStartDate": null,
    "Updated": "2025-04-17T09:22:06",
    "PhotoUrl": "https://s3-us-west-2.amazonaws.com/static.fantasydata.com/headshots/soc/low-res/0.png",
    "RotoWirePlayerID": null,
    "DraftKingsPosition": null,
    "UsaTodayPlayerID": null,
    "UsaTodayHeadshotUrl": null,
    "UsaTodayHeadshotNoBackgroundUrl": null,
    "UsaTodayHeadshotUpdated": null,
    "UsaTodayHeadshotNoBackgroundUpdated": null
  },
  {
    "PlayerId": 90106518,
    "FirstName": "Marawan Attia Fahim",
    "LastName": "Ghallab",
    "CommonName": "Marawan Attia",
    "ShortName": "Marawan Attia",
    "Position": "M",
    "PositionCategory": "M",
    "Jersey": 13,
    "Foot": "Right",
    "Height": null,
    "Weight": null,
    "Gender": "Male",
    "BirthDate": "1998-08-01T00:00:00",
    "BirthCity": null,
    "BirthCountry": "Egypt",
    "Nationality": "Egypt",
    "InjuryStatus": "Scrambled",
    "InjuryBodyPart": "Scrambled",
    "InjuryNotes": "Scrambled",
    "InjuryStartDate": null,
    "Updated": "2025-06-14T19:08:38",
    "PhotoUrl": "https://s3-us-west-2.amazonaws.com/static.fantasydata.com/headshots/soc/low-res/0.png",
    "RotoWirePlayerID": null,
    "DraftKingsPosition": null,
    "UsaTodayPlayerID": null,
    "UsaTodayHeadshotUrl": null,
    "UsaTodayHeadshotNoBackgroundUrl": null,
    "UsaTodayHeadshotUpdated": null,
    "UsaTodayHeadshotNoBackgroundUpdated": null
  },
  {
    "PlayerId": 90111412,
    "FirstName": "Ahmed Ramadan Abdou",
    "LastName": "Mohamed",
    "CommonName": "Ahmed Beckham",
    "ShortName": "Ahmed Beckham",
    "Position": "D",
    "PositionCategory": "D",
    "Jersey": 4,
    "Foot": "Right",
    "Height": null,
    "Weight": null,
    "Gender": "Male",
    "BirthDate": "1997-03-23T00:00:00",
    "BirthCity": null,
    "BirthCountry": "Egypt",
    "Nationality": "Egypt",
    "InjuryStatus": "Scrambled",
    "InjuryBodyPart": "Scrambled",
    "InjuryNotes": "Scrambled",
    "InjuryStartDate": null,
    "Updated": "2025-06-20T16:08:07",
    "PhotoUrl": "https://s3-us-west-2.amazonaws.com/static.fantasydata.com/headshots/soc/low-res/0.png",
    "RotoWirePlayerID": null,
    "DraftKingsPosition": null,
    "UsaTodayPlayerID": null,
    "UsaTodayHeadshotUrl": null,
    "UsaTodayHeadshotNoBackgroundUrl": null,
    "UsaTodayHeadshotUpdated": null,
    "UsaTodayHeadshotNoBackgroundUpdated": null
  },
  {
    "PlayerId": 90115516,
    "FirstName": "Ahmed Nabil Ashour",
    "LastName": "Abdelaal",
    "CommonName": "Ahmed Nabil Koka",
    "ShortName": "Ahmed Nabil Koka",
    "Position": "M",
    "PositionCategory": "M",
    "Jersey": 36,
    "Foot": "Left",
    "Height": 177,
    "Weight": 71,
    "Gender": "Male",
    "BirthDate": "2001-07-04T00:00:00",
    "BirthCity": null,
    "BirthCountry": "Egypt",
    "Nationality": "Egypt",
    "InjuryStatus": "Scrambled",
    "InjuryBodyPart": "Scrambled",
    "InjuryNotes": "Scrambled",
    "InjuryStartDate": null,
    "Updated": "2025-06-14T19:08:38",
    "PhotoUrl": "https://s3-us-west-2.amazonaws.com/static.fantasydata.com/headshots/soc/low-res/0.png",
    "RotoWirePlayerID": null,
    "DraftKingsPosition": null,
    "UsaTodayPlayerID": null,
    "UsaTodayHeadshotUrl": null,
    "UsaTodayHeadshotNoBackgroundUrl": null,
    "UsaTodayHeadshotUpdated": null,
    "UsaTodayHeadshotNoBackgroundUpdated": null
  },
  {
    "PlayerId": 90117742,
    "FirstName": "Nejc",
    "LastName": "Gradišar",
    "CommonName": "Nejc Gradišar",
    "ShortName": "N. Gradišar",
    "Position": "A",
    "PositionCategory": "A",
    "Jersey": 10,
    "Foot": null,
    "Height": null,
    "Weight": null,
    "Gender": "Male",
    "BirthDate": "2002-08-06T00:00:00",
    "BirthCity": "Ljubljana",
    "BirthCountry": "Slovenia",
    "Nationality": "Slovenia",
    "InjuryStatus": "Scrambled",
    "InjuryBodyPart": "Scrambled",
    "InjuryNotes": "Scrambled",
    "InjuryStartDate": null,
    "Updated": "2025-06-14T19:08:38",
    "PhotoUrl": "https://s3-us-west-2.amazonaws.com/static.fantasydata.com/headshots/soc/low-res/0.png",
    "RotoWirePlayerID": null,
    "DraftKingsPosition": null,
    "UsaTodayPlayerID": null,
    "UsaTodayHeadshotUrl": null,
    "UsaTodayHeadshotNoBackgroundUrl": null,
    "UsaTodayHeadshotUpdated": null,
    "UsaTodayHeadshotNoBackgroundUpdated": null
  },
  {
    "PlayerId": 90119796,
    "FirstName": "Mostafa Ahmed Abdelaziz Mohamed",
    "LastName": "Shoubir",
    "CommonName": "Mostafa Shoubir",
    "ShortName": "Mostafa Shoubir",
    "Position": "GK",
    "PositionCategory": "GK",
    "Jersey": 31,
    "Foot": null,
    "Height": null,
    "Weight": null,
    "Gender": "Male",
    "BirthDate": "2000-05-15T00:00:00",
    "BirthCity": null,
    "BirthCountry": "Egypt",
    "Nationality": "Egypt",
    "InjuryStatus": "Scrambled",
    "InjuryBodyPart": "Scrambled",
    "InjuryNotes": "Scrambled",
    "InjuryStartDate": null,
    "Updated": "2025-06-14T19:08:38",
    "PhotoUrl": "https://s3-us-west-2.amazonaws.com/static.fantasydata.com/headshots/soc/low-res/0.png",
    "RotoWirePlayerID": null,
    "DraftKingsPosition": null,
    "UsaTodayPlayerID": null,
    "UsaTodayHeadshotUrl": null,
    "UsaTodayHeadshotNoBackgroundUrl": null,
    "UsaTodayHeadshotUpdated": null,
    "UsaTodayHeadshotNoBackgroundUpdated": null
  },
  {
    "PlayerId": 90121445,
    "FirstName": "Wessam Haitham Mohammed",
    "LastName": "Abou Ali",
    "CommonName": "Wessam Abou Ali",
    "ShortName": "Wessam Abou Ali",
    "Position": "A",
    "PositionCategory": "A",
    "Jersey": 9,
    "Foot": null,
    "Height": null,
    "Weight": null,
    "Gender": "Male",
    "BirthDate": "1999-01-04T00:00:00",
    "BirthCity": "Aalborg",
    "BirthCountry": "Denmark",
    "Nationality": "Palestine",
    "InjuryStatus": "Scrambled",
    "InjuryBodyPart": "Scrambled",
    "InjuryNotes": "Scrambled",
    "InjuryStartDate": null,
    "Updated": "2025-06-14T19:08:38",
    "PhotoUrl": "https://s3-us-west-2.amazonaws.com/static.fantasydata.com/headshots/soc/low-res/0.png",
    "RotoWirePlayerID": null,
    "DraftKingsPosition": null,
    "UsaTodayPlayerID": null,
    "UsaTodayHeadshotUrl": null,
    "UsaTodayHeadshotNoBackgroundUrl": null,
    "UsaTodayHeadshotUpdated": null,
    "UsaTodayHeadshotNoBackgroundUpdated": null
  },
  {
    "PlayerId": 90132033,
    "FirstName": "Mostafa Mohamed Makhlouf",
    "LastName": "Amin",
    "CommonName": "Mostafa Makhlouf",
    "ShortName": "Mostafa Makhlouf",
    "Position": "GK",
    "PositionCategory": "GK",
    "Jersey": 37,
    "Foot": null,
    "Height": null,
    "Weight": null,
    "Gender": "Male",
    "BirthDate": "2003-03-11T00:00:00",
    "BirthCity": null,
    "BirthCountry": "Egypt",
    "Nationality": "Egypt",
    "InjuryStatus": "Scrambled",
    "InjuryBodyPart": "Scrambled",
    "InjuryNotes": "Scrambled",
    "InjuryStartDate": null,
    "Updated": "2025-06-19T11:00:15",
    "PhotoUrl": "https://s3-us-west-2.amazonaws.com/static.fantasydata.com/headshots/soc/low-res/0.png",
    "RotoWirePlayerID": null,
    "DraftKingsPosition": null,
    "UsaTodayPlayerID": null,
    "UsaTodayHeadshotUrl": null,
    "UsaTodayHeadshotNoBackgroundUrl": null,
    "UsaTodayHeadshotUpdated": null,
    "UsaTodayHeadshotNoBackgroundUpdated": null
  },
  {
    "PlayerId": 90132034,
    "FirstName": "Moaataz Mohamed Ibrahim",
    "LastName": "Masoud",
    "CommonName": "Moaataz Mohamed",
    "ShortName": "Moaataz Mohamed",
    "Position": "D",
    "PositionCategory": "D",
    "Jersey": null,
    "Foot": null,
    "Height": null,
    "Weight": null,
    "Gender": "Male",
    "BirthDate": "2005-03-20T00:00:00",
    "BirthCity": null,
    "BirthCountry": "Egypt",
    "Nationality": "Egypt",
    "InjuryStatus": "Scrambled",
    "InjuryBodyPart": "Scrambled",
    "InjuryNotes": "Scrambled",
    "InjuryStartDate": null,
    "Updated": "2025-04-27T11:13:27",
    "PhotoUrl": "https://s3-us-west-2.amazonaws.com/static.fantasydata.com/headshots/soc/low-res/0.png",
    "RotoWirePlayerID": null,
    "DraftKingsPosition": null,
    "UsaTodayPlayerID": null,
    "UsaTodayHeadshotUrl": null,
    "UsaTodayHeadshotNoBackgroundUrl": null,
    "UsaTodayHeadshotUpdated": null,
    "UsaTodayHeadshotNoBackgroundUpdated": null
  },
  {
    "PlayerId": 90132036,
    "FirstName": "Mostafa Mahmoud Abdelkader",
    "LastName": "Saleh",
    "CommonName": "Mostafa El Aash",
    "ShortName": "Mostafa El Aash",
    "Position": "D",
    "PositionCategory": "D",
    "Jersey": 27,
    "Foot": null,
    "Height": null,
    "Weight": null,
    "Gender": "Male",
    "BirthDate": "2000-10-11T00:00:00",
    "BirthCity": null,
    "BirthCountry": "Egypt",
    "Nationality": "Egypt",
    "InjuryStatus": "Scrambled",
    "InjuryBodyPart": "Scrambled",
    "InjuryNotes": "Scrambled",
    "InjuryStartDate": null,
    "Updated": "2025-06-14T19:08:38",
    "PhotoUrl": "https://s3-us-west-2.amazonaws.com/static.fantasydata.com/headshots/soc/low-res/0.png",
    "RotoWirePlayerID": null,
    "DraftKingsPosition": null,
    "UsaTodayPlayerID": null,
    "UsaTodayHeadshotUrl": null,
    "UsaTodayHeadshotNoBackgroundUrl": null,
    "UsaTodayHeadshotUpdated": null,
    "UsaTodayHeadshotNoBackgroundUpdated": null
  },
  {
    "PlayerId": 90132039,
    "FirstName": "Khaled Mohamed Abdelfattah",
    "LastName": "Ibrahim",
    "CommonName": "Khaled Abdelfattah",
    "ShortName": "Khaled Abdelfattah",
    "Position": "D",
    "PositionCategory": "D",
    "Jersey": 2,
    "Foot": "Both",
    "Height": null,
    "Weight": null,
    "Gender": "Male",
    "BirthDate": "1999-01-22T00:00:00",
    "BirthCity": null,
    "BirthCountry": "Egypt",
    "Nationality": "Egypt",
    "InjuryStatus": "Scrambled",
    "InjuryBodyPart": "Scrambled",
    "InjuryNotes": "Scrambled",
    "InjuryStartDate": null,
    "Updated": "2025-06-14T19:08:38",
    "PhotoUrl": "https://s3-us-west-2.amazonaws.com/static.fantasydata.com/headshots/soc/low-res/0.png",
    "RotoWirePlayerID": null,
    "DraftKingsPosition": null,
    "UsaTodayPlayerID": null,
    "UsaTodayHeadshotUrl": null,
    "UsaTodayHeadshotNoBackgroundUrl": null,
    "UsaTodayHeadshotUpdated": null,
    "UsaTodayHeadshotNoBackgroundUpdated": null
  },
  {
    "PlayerId": 90132046,
    "FirstName": "Ahmed Reda Hashem",
    "LastName": "Ahmed",
    "CommonName": "Ahmed Reda",
    "ShortName": "Ahmed Reda",
    "Position": "M",
    "PositionCategory": "M",
    "Jersey": 24,
    "Foot": null,
    "Height": null,
    "Weight": null,
    "Gender": "Male",
    "BirthDate": "2000-02-19T00:00:00",
    "BirthCity": null,
    "BirthCountry": "Egypt",
    "Nationality": "Egypt",
    "InjuryStatus": "Scrambled",
    "InjuryBodyPart": "Scrambled",
    "InjuryNotes": "Scrambled",
    "InjuryStartDate": null,
    "Updated": "2025-06-17T06:45:23",
    "PhotoUrl": "https://s3-us-west-2.amazonaws.com/static.fantasydata.com/headshots/soc/low-res/0.png",
    "RotoWirePlayerID": null,
    "DraftKingsPosition": null,
    "UsaTodayPlayerID": null,
    "UsaTodayHeadshotUrl": null,
    "UsaTodayHeadshotNoBackgroundUrl": null,
    "UsaTodayHeadshotUpdated": null,
    "UsaTodayHeadshotNoBackgroundUpdated": null
  },
  {
    "PlayerId": 90132048,
    "FirstName": "Karim Mohamed Abdelhamid Mahmoud",
    "LastName": "Hassan",
    "CommonName": "Karim El Debes",
    "ShortName": "Karim El Debes",
    "Position": "M",
    "PositionCategory": "M",
    "Jersey": 11,
    "Foot": "Left",
    "Height": 169,
    "Weight": null,
    "Gender": "Male",
    "BirthDate": "2003-06-03T00:00:00",
    "BirthCity": null,
    "BirthCountry": "Egypt",
    "Nationality": "Egypt",
    "InjuryStatus": "Scrambled",
    "InjuryBodyPart": "Scrambled",
    "InjuryNotes": "Scrambled",
    "InjuryStartDate": null,
    "Updated": "2025-06-14T19:08:38",
    "PhotoUrl": "https://s3-us-west-2.amazonaws.com/static.fantasydata.com/headshots/soc/low-res/0.png",
    "RotoWirePlayerID": null,
    "DraftKingsPosition": null,
    "UsaTodayPlayerID": null,
    "UsaTodayHeadshotUrl": null,
    "UsaTodayHeadshotNoBackgroundUrl": null,
    "UsaTodayHeadshotUpdated": null,
    "UsaTodayHeadshotNoBackgroundUpdated": null
  },
  {
    "PlayerId": 90132049,
    "FirstName": "Mohamed Abdalla Ali",
    "LastName": "Youssef",
    "CommonName": "Mohamed Abdalla",
    "ShortName": "Mohamed Abdalla",
    "Position": "M",
    "PositionCategory": "M",
    "Jersey": null,
    "Foot": null,
    "Height": null,
    "Weight": null,
    "Gender": "Male",
    "BirthDate": "2005-10-18T00:00:00",
    "BirthCity": null,
    "BirthCountry": "Egypt",
    "Nationality": "Egypt",
    "InjuryStatus": "Scrambled",
    "InjuryBodyPart": "Scrambled",
    "InjuryNotes": "Scrambled",
    "InjuryStartDate": null,
    "Updated": "2025-06-12T18:00:45",
    "PhotoUrl": "https://s3-us-west-2.amazonaws.com/static.fantasydata.com/headshots/soc/low-res/0.png",
    "RotoWirePlayerID": null,
    "DraftKingsPosition": null,
    "UsaTodayPlayerID": null,
    "UsaTodayHeadshotUrl": null,
    "UsaTodayHeadshotNoBackgroundUrl": null,
    "UsaTodayHeadshotUpdated": null,
    "UsaTodayHeadshotNoBackgroundUpdated": null
  },
  {
    "PlayerId": 90132050,
    "FirstName": "Karim Walid Sayed Saleh",
    "LastName": "Hassan",
    "CommonName": "Karim Nedved",
    "ShortName": "Karim Nedved",
    "Position": "M",
    "PositionCategory": "M",
    "Jersey": null,
    "Foot": "Right",
    "Height": 183,
    "Weight": null,
    "Gender": "Male",
    "BirthDate": "1997-08-08T00:00:00",
    "BirthCity": null,
    "BirthCountry": "Egypt",
    "Nationality": "Egypt",
    "InjuryStatus": "Scrambled",
    "InjuryBodyPart": "Scrambled",
    "InjuryNotes": "Scrambled",
    "InjuryStartDate": null,
    "Updated": "2025-04-17T09:25:14",
    "PhotoUrl": "https://s3-us-west-2.amazonaws.com/static.fantasydata.com/headshots/soc/low-res/0.png",
    "RotoWirePlayerID": null,
    "DraftKingsPosition": null,
    "UsaTodayPlayerID": null,
    "UsaTodayHeadshotUrl": null,
    "UsaTodayHeadshotNoBackgroundUrl": null,
    "UsaTodayHeadshotUpdated": null,
    "UsaTodayHeadshotNoBackgroundUpdated": null
  },
  {
    "PlayerId": 90132054,
    "FirstName": "Samir Mohamed El Sayed Abdelaziz",
    "LastName": "Galal",
    "CommonName": "Samir Mohamed",
    "ShortName": "Samir Mohamed",
    "Position": "A",
    "PositionCategory": "A",
    "Jersey": null,
    "Foot": null,
    "Height": 180,
    "Weight": null,
    "Gender": "Male",
    "BirthDate": "2003-09-04T00:00:00",
    "BirthCity": null,
    "BirthCountry": "Egypt",
    "Nationality": "Egypt",
    "InjuryStatus": "Scrambled",
    "InjuryBodyPart": "Scrambled",
    "InjuryNotes": "Scrambled",
    "InjuryStartDate": null,
    "Updated": "2025-04-17T09:26:45",
    "PhotoUrl": "https://s3-us-west-2.amazonaws.com/static.fantasydata.com/headshots/soc/low-res/0.png",
    "RotoWirePlayerID": null,
    "DraftKingsPosition": null,
    "UsaTodayPlayerID": null,
    "UsaTodayHeadshotUrl": null,
    "UsaTodayHeadshotNoBackgroundUrl": null,
    "UsaTodayHeadshotUpdated": null,
    "UsaTodayHeadshotNoBackgroundUpdated": null
  },
  {
    "PlayerId": 90132055,
    "FirstName": "Mohamed Ahmed Fathallah",
    "LastName": "Zaalouk",
    "CommonName": "Mohamed Ahmed Zaalouk",
    "ShortName": "Mohamed Ahmed Zaalouk",
    "Position": "A",
    "PositionCategory": "A",
    "Jersey": null,
    "Foot": null,
    "Height": null,
    "Weight": null,
    "Gender": "Male",
    "BirthDate": "2005-03-05T00:00:00",
    "BirthCity": null,
    "BirthCountry": "Egypt",
    "Nationality": "Egypt",
    "InjuryStatus": "Scrambled",
    "InjuryBodyPart": "Scrambled",
    "InjuryNotes": "Scrambled",
    "InjuryStartDate": null,
    "Updated": "2025-05-09T13:37:30",
    "PhotoUrl": "https://s3-us-west-2.amazonaws.com/static.fantasydata.com/headshots/soc/low-res/0.png",
    "RotoWirePlayerID": null,
    "DraftKingsPosition": null,
    "UsaTodayPlayerID": null,
    "UsaTodayHeadshotUrl": null,
    "UsaTodayHeadshotNoBackgroundUrl": null,
    "UsaTodayHeadshotUpdated": null,
    "UsaTodayHeadshotNoBackgroundUpdated": null
  },
  {
    "PlayerId": 90132056,
    "FirstName": "Hamza Mohamed",
    "LastName": "Abdelkerem",
    "CommonName": "Hamza Abdelkerem",
    "ShortName": "Hamza Abdelkerem",
    "Position": "A",
    "PositionCategory": "A",
    "Jersey": null,
    "Foot": null,
    "Height": null,
    "Weight": null,
    "Gender": "Male",
    "BirthDate": "2008-01-01T00:00:00",
    "BirthCity": null,
    "BirthCountry": "Egypt",
    "Nationality": "Egypt",
    "InjuryStatus": "Scrambled",
    "InjuryBodyPart": "Scrambled",
    "InjuryNotes": "Scrambled",
    "InjuryStartDate": null,
    "Updated": "2025-04-17T09:27:03",
    "PhotoUrl": "https://s3-us-west-2.amazonaws.com/static.fantasydata.com/headshots/soc/low-res/0.png",
    "RotoWirePlayerID": null,
    "DraftKingsPosition": null,
    "UsaTodayPlayerID": null,
    "UsaTodayHeadshotUrl": null,
    "UsaTodayHeadshotNoBackgroundUrl": null,
    "UsaTodayHeadshotUpdated": null,
    "UsaTodayHeadshotNoBackgroundUpdated": null
  },
  {
    "PlayerId": 90133338,
    "FirstName": "Mohamed Ahmed El Sayed",
    "LastName": "Abdou",
    "CommonName": "Mohamed Seha",
    "ShortName": "Mohamed Seha",
    "Position": "GK",
    "PositionCategory": "GK",
    "Jersey": 26,
    "Foot": null,
    "Height": null,
    "Weight": null,
    "Gender": "Male",
    "BirthDate": "2001-05-01T00:00:00",
    "BirthCity": null,
    "BirthCountry": "Egypt",
    "Nationality": "Egypt",
    "InjuryStatus": "Scrambled",
    "InjuryBodyPart": "Scrambled",
    "InjuryNotes": "Scrambled",
    "InjuryStartDate": null,
    "Updated": "2025-06-19T11:00:15",
    "PhotoUrl": "https://s3-us-west-2.amazonaws.com/static.fantasydata.com/headshots/soc/low-res/0.png",
    "RotoWirePlayerID": null,
    "DraftKingsPosition": null,
    "UsaTodayPlayerID": null,
    "UsaTodayHeadshotUrl": null,
    "UsaTodayHeadshotNoBackgroundUrl": null,
    "UsaTodayHeadshotUpdated": null,
    "UsaTodayHeadshotNoBackgroundUpdated": null
  }
]