[
  {
    "PlayerId": 90044682,
    "FirstName": "Yan",
    "LastName": "Medeiro Sasse",
    "CommonName": "Yan Sasse",
    "ShortName": "Yan Sasse",
    "Position": "M",
    "PositionCategory": "M",
    "Jersey": 10,
    "Foot": "Right",
    "Height": 173,
    "Weight": 67,
    "Gender": "Male",
    "BirthDate": "1997-06-24T00:00:00",
    "BirthCity": "Porto Alegre, RS",
    "BirthCountry": "Brazil",
    "Nationality": "Brazil",
    "InjuryStatus": "Scrambled",
    "InjuryBodyPart": "Scrambled",
    "InjuryNotes": "Scrambled",
    "InjuryStartDate": null,
    "Updated": "2025-06-16T19:53:23",
    "PhotoUrl": "https://s3-us-west-2.amazonaws.com/static.fantasydata.com/headshots/soc/low-res/0.png",
    "RotoWirePlayerID": null,
    "DraftKingsPosition": null,
    "UsaTodayPlayerID": null,
    "UsaTodayHeadshotUrl": null,
    "UsaTodayHeadshotNoBackgroundUrl": null,
    "UsaTodayHeadshotUpdated": null,
    "UsaTodayHeadshotNoBackgroundUpdated": null
  },
  {
    "PlayerId": 90045527,
    "FirstName": "Aymen",
    "LastName": "Ben Mohamed",
    "CommonName": "Aymen Ben Mohamed",
    "ShortName": "A. Ben Mohamed",
    "Position": "M",
    "PositionCategory": "M",
    "Jersey": 22,
    "Foot": "Left",
    "Height": 175,
    "Weight": null,
    "Gender": "Male",
    "BirthDate": "1994-12-08T00:00:00",
    "BirthCity": "London",
    "BirthCountry": "England",
    "Nationality": "Tunisia",
    "InjuryStatus": "Scrambled",
    "InjuryBodyPart": "Scrambled",
    "InjuryNotes": "Scrambled",
    "InjuryStartDate": null,
    "Updated": "2025-06-16T19:53:23",
    "PhotoUrl": "https://s3-us-west-2.amazonaws.com/static.fantasydata.com/headshots/soc/low-res/0.png",
    "RotoWirePlayerID": null,
    "DraftKingsPosition": null,
    "UsaTodayPlayerID": null,
    "UsaTodayHeadshotUrl": null,
    "UsaTodayHeadshotNoBackgroundUrl": null,
    "UsaTodayHeadshotUpdated": null,
    "UsaTodayHeadshotNoBackgroundUpdated": null
  },
  {
    "PlayerId": 90046378,
    "FirstName": "Yassine",
    "LastName": "Meriah",
    "CommonName": "Yassine Meriah",
    "ShortName": "Y. Meriah",
    "Position": "D",
    "PositionCategory": "D",
    "Jersey": 5,
    "Foot": "Right",
    "Height": 180,
    "Weight": 80,
    "Gender": "Male",
    "BirthDate": "1993-07-02T00:00:00",
    "BirthCity": "Tunis",
    "BirthCountry": "Tunisia",
    "Nationality": "Tunisia",
    "InjuryStatus": "Scrambled",
    "InjuryBodyPart": "Scrambled",
    "InjuryNotes": "Scrambled",
    "InjuryStartDate": null,
    "Updated": "2025-07-04T07:54:52",
    "PhotoUrl": "https://s3-us-west-2.amazonaws.com/static.fantasydata.com/headshots/soc/low-res/90046378.png",
    "RotoWirePlayerID": null,
    "DraftKingsPosition": "D",
    "UsaTodayPlayerID": null,
    "UsaTodayHeadshotUrl": null,
    "UsaTodayHeadshotNoBackgroundUrl": null,
    "UsaTodayHeadshotUpdated": null,
    "UsaTodayHeadshotNoBackgroundUpdated": null
  },
  {
    "PlayerId": 90047585,
    "FirstName": "Rodrigo",
    "LastName": "Rodrigues Silva",
    "CommonName": "Rodrigo Rodrigues",
    "ShortName": "Rodrigo Rodrigues",
    "Position": "A",
    "PositionCategory": "A",
    "Jersey": 9,
    "Foot": "Right",
    "Height": 191,
    "Weight": 86,
    "Gender": "Male",
    "BirthDate": "1996-06-18T00:00:00",
    "BirthCity": "Fortaleza, CE",
    "BirthCountry": "Brazil",
    "Nationality": "Brazil",
    "InjuryStatus": "Scrambled",
    "InjuryBodyPart": "Scrambled",
    "InjuryNotes": "Scrambled",
    "InjuryStartDate": null,
    "Updated": "2025-06-16T19:53:23",
    "PhotoUrl": "https://s3-us-west-2.amazonaws.com/static.fantasydata.com/headshots/soc/low-res/0.png",
    "RotoWirePlayerID": null,
    "DraftKingsPosition": null,
    "UsaTodayPlayerID": null,
    "UsaTodayHeadshotUrl": null,
    "UsaTodayHeadshotNoBackgroundUrl": null,
    "UsaTodayHeadshotUpdated": null,
    "UsaTodayHeadshotNoBackgroundUpdated": null
  },
  {
    "PlayerId": 90052117,
    "FirstName": "Hamza",
    "LastName": "Jelassi",
    "CommonName": "Hamza Jelassi",
    "ShortName": "H. Jelassi",
    "Position": "D",
    "PositionCategory": "D",
    "Jersey": 6,
    "Foot": "Right",
    "Height": null,
    "Weight": null,
    "Gender": "Male",
    "BirthDate": "1991-09-29T00:00:00",
    "BirthCity": null,
    "BirthCountry": "Tunisia",
    "Nationality": "Tunisia",
    "InjuryStatus": "Scrambled",
    "InjuryBodyPart": "Scrambled",
    "InjuryNotes": "Scrambled",
    "InjuryStartDate": null,
    "Updated": "2025-06-16T19:53:23",
    "PhotoUrl": "https://s3-us-west-2.amazonaws.com/static.fantasydata.com/headshots/soc/low-res/0.png",
    "RotoWirePlayerID": null,
    "DraftKingsPosition": null,
    "UsaTodayPlayerID": null,
    "UsaTodayHeadshotUrl": null,
    "UsaTodayHeadshotNoBackgroundUrl": null,
    "UsaTodayHeadshotUpdated": null,
    "UsaTodayHeadshotNoBackgroundUpdated": null
  },
  {
    "PlayerId": 90054797,
    "FirstName": "Mohammed Youcef",
    "LastName": "Belaili",
    "CommonName": "Youcef Belaili",
    "ShortName": "Y. Belaili",
    "Position": "M",
    "PositionCategory": "M",
    "Jersey": 11,
    "Foot": "Right",
    "Height": 178,
    "Weight": 75,
    "Gender": "Male",
    "BirthDate": "1992-03-14T00:00:00",
    "BirthCity": "Oran",
    "BirthCountry": "Algeria",
    "Nationality": "Algeria",
    "InjuryStatus": "Scrambled",
    "InjuryBodyPart": "Scrambled",
    "InjuryNotes": "Scrambled",
    "InjuryStartDate": null,
    "Updated": "2025-06-16T19:53:23",
    "PhotoUrl": "https://s3-us-west-2.amazonaws.com/static.fantasydata.com/headshots/soc/low-res/90054797.png",
    "RotoWirePlayerID": null,
    "DraftKingsPosition": "M",
    "UsaTodayPlayerID": null,
    "UsaTodayHeadshotUrl": null,
    "UsaTodayHeadshotNoBackgroundUrl": null,
    "UsaTodayHeadshotUpdated": null,
    "UsaTodayHeadshotNoBackgroundUpdated": null
  },
  {
    "PlayerId": 90090174,
    "FirstName": "Bechir",
    "LastName": "Ben Said",
    "CommonName": "Bechir Ben Said",
    "ShortName": "B. Ben Said",
    "Position": "GK",
    "PositionCategory": "GK",
    "Jersey": 32,
    "Foot": null,
    "Height": 190,
    "Weight": 73,
    "Gender": "Male",
    "BirthDate": "1992-11-29T00:00:00",
    "BirthCity": null,
    "BirthCountry": "Tunisia",
    "Nationality": "Tunisia",
    "InjuryStatus": "Scrambled",
    "InjuryBodyPart": "Scrambled",
    "InjuryNotes": "Scrambled",
    "InjuryStartDate": null,
    "Updated": "2025-06-16T19:53:23",
    "PhotoUrl": "https://s3-us-west-2.amazonaws.com/static.fantasydata.com/headshots/soc/low-res/90090174.png",
    "RotoWirePlayerID": null,
    "DraftKingsPosition": "GK",
    "UsaTodayPlayerID": null,
    "UsaTodayHeadshotUrl": null,
    "UsaTodayHeadshotNoBackgroundUrl": null,
    "UsaTodayHeadshotUpdated": null,
    "UsaTodayHeadshotNoBackgroundUpdated": null
  },
  {
    "PlayerId": 90098562,
    "FirstName": "Roger Ben Boris",
    "LastName": "Aholou",
    "CommonName": "Roger Aholou",
    "ShortName": "R. Aholou",
    "Position": "M",
    "PositionCategory": "M",
    "Jersey": 5,
    "Foot": "Right",
    "Height": 182,
    "Weight": 71,
    "Gender": "Male",
    "BirthDate": "1995-12-30T00:00:00",
    "BirthCity": null,
    "BirthCountry": "Côte d’Ivoire",
    "Nationality": "Togo",
    "InjuryStatus": "Scrambled",
    "InjuryBodyPart": "Scrambled",
    "InjuryNotes": "Scrambled",
    "InjuryStartDate": null,
    "Updated": "2025-06-14T14:07:26",
    "PhotoUrl": "https://s3-us-west-2.amazonaws.com/static.fantasydata.com/headshots/soc/low-res/90098562.png",
    "RotoWirePlayerID": null,
    "DraftKingsPosition": null,
    "UsaTodayPlayerID": null,
    "UsaTodayHeadshotUrl": null,
    "UsaTodayHeadshotNoBackgroundUrl": null,
    "UsaTodayHeadshotUpdated": null,
    "UsaTodayHeadshotNoBackgroundUpdated": null
  },
  {
    "PlayerId": 90100005,
    "FirstName": "Mohamed Amine",
    "LastName": "Tougaï",
    "CommonName": "Mohamed Amine Tougaï",
    "ShortName": "M. Tougaï",
    "Position": "D",
    "PositionCategory": "D",
    "Jersey": 15,
    "Foot": null,
    "Height": 191,
    "Weight": null,
    "Gender": "Male",
    "BirthDate": "2000-01-22T00:00:00",
    "BirthCity": null,
    "BirthCountry": "Algeria",
    "Nationality": "Algeria",
    "InjuryStatus": "Scrambled",
    "InjuryBodyPart": "Scrambled",
    "InjuryNotes": "Scrambled",
    "InjuryStartDate": null,
    "Updated": "2025-06-16T19:53:23",
    "PhotoUrl": "https://s3-us-west-2.amazonaws.com/static.fantasydata.com/headshots/soc/low-res/90100005.png",
    "RotoWirePlayerID": null,
    "DraftKingsPosition": null,
    "UsaTodayPlayerID": null,
    "UsaTodayHeadshotUrl": null,
    "UsaTodayHeadshotNoBackgroundUrl": null,
    "UsaTodayHeadshotUpdated": null,
    "UsaTodayHeadshotNoBackgroundUpdated": null
  },
  {
    "PlayerId": 90100022,
    "FirstName": "Mohamed Amine",
    "LastName": "Ben Hamida",
    "CommonName": "Mohamed Amine Ben Hamida",
    "ShortName": "M. Ben Hamida",
    "Position": "D",
    "PositionCategory": "D",
    "Jersey": 20,
    "Foot": "Left",
    "Height": 187,
    "Weight": null,
    "Gender": "Male",
    "BirthDate": "1995-12-15T00:00:00",
    "BirthCity": null,
    "BirthCountry": "Tunisia",
    "Nationality": "Tunisia",
    "InjuryStatus": "Scrambled",
    "InjuryBodyPart": "Scrambled",
    "InjuryNotes": "Scrambled",
    "InjuryStartDate": null,
    "Updated": "2025-06-16T19:53:23",
    "PhotoUrl": "https://s3-us-west-2.amazonaws.com/static.fantasydata.com/headshots/soc/low-res/90100022.png",
    "RotoWirePlayerID": null,
    "DraftKingsPosition": null,
    "UsaTodayPlayerID": null,
    "UsaTodayHeadshotUrl": null,
    "UsaTodayHeadshotNoBackgroundUrl": null,
    "UsaTodayHeadshotUpdated": null,
    "UsaTodayHeadshotNoBackgroundUpdated": null
  },
  {
    "PlayerId": 90103901,
    "FirstName": "Mohamed Sedki",
    "LastName": "Debchi",
    "CommonName": "Mohamed Sedki Debchi",
    "ShortName": "M. Debchi",
    "Position": "GK",
    "PositionCategory": "GK",
    "Jersey": 26,
    "Foot": "Right",
    "Height": 195,
    "Weight": null,
    "Gender": "Male",
    "BirthDate": "1999-10-28T00:00:00",
    "BirthCity": "Gabès",
    "BirthCountry": "Tunisia",
    "Nationality": "Tunisia",
    "InjuryStatus": "Scrambled",
    "InjuryBodyPart": "Scrambled",
    "InjuryNotes": "Scrambled",
    "InjuryStartDate": null,
    "Updated": "2025-06-16T19:53:23",
    "PhotoUrl": "https://s3-us-west-2.amazonaws.com/static.fantasydata.com/headshots/soc/low-res/0.png",
    "RotoWirePlayerID": null,
    "DraftKingsPosition": null,
    "UsaTodayPlayerID": null,
    "UsaTodayHeadshotUrl": null,
    "UsaTodayHeadshotNoBackgroundUrl": null,
    "UsaTodayHeadshotUpdated": null,
    "UsaTodayHeadshotNoBackgroundUpdated": null
  },
  {
    "PlayerId": 90107843,
    "FirstName": "Abdramane",
    "LastName": "Konaté",
    "CommonName": "Abdramane Konaté",
    "ShortName": "A. Konaté",
    "Position": "A",
    "PositionCategory": "A",
    "Jersey": 21,
    "Foot": null,
    "Height": null,
    "Weight": null,
    "Gender": "Male",
    "BirthDate": "2006-06-25T00:00:00",
    "BirthCity": null,
    "BirthCountry": "Côte d’Ivoire",
    "Nationality": "Côte d’Ivoire",
    "InjuryStatus": "Scrambled",
    "InjuryBodyPart": "Scrambled",
    "InjuryNotes": "Scrambled",
    "InjuryStartDate": null,
    "Updated": "2025-06-16T19:53:23",
    "PhotoUrl": "https://s3-us-west-2.amazonaws.com/static.fantasydata.com/headshots/soc/low-res/0.png",
    "RotoWirePlayerID": null,
    "DraftKingsPosition": null,
    "UsaTodayPlayerID": null,
    "UsaTodayHeadshotUrl": null,
    "UsaTodayHeadshotNoBackgroundUrl": null,
    "UsaTodayHeadshotUpdated": null,
    "UsaTodayHeadshotNoBackgroundUpdated": null
  },
  {
    "PlayerId": 90111537,
    "FirstName": "Mohamed Wael",
    "LastName": "Derbali",
    "CommonName": "Mohamed Wael Derbali",
    "ShortName": "M. Derbali",
    "Position": "M",
    "PositionCategory": "M",
    "Jersey": 4,
    "Foot": null,
    "Height": null,
    "Weight": null,
    "Gender": "Male",
    "BirthDate": "2003-06-18T00:00:00",
    "BirthCity": null,
    "BirthCountry": "Tunisia",
    "Nationality": "Tunisia",
    "InjuryStatus": "Scrambled",
    "InjuryBodyPart": "Scrambled",
    "InjuryNotes": "Scrambled",
    "InjuryStartDate": null,
    "Updated": "2025-06-16T19:53:23",
    "PhotoUrl": "https://s3-us-west-2.amazonaws.com/static.fantasydata.com/headshots/soc/low-res/0.png",
    "RotoWirePlayerID": null,
    "DraftKingsPosition": null,
    "UsaTodayPlayerID": null,
    "UsaTodayHeadshotUrl": null,
    "UsaTodayHeadshotNoBackgroundUrl": null,
    "UsaTodayHeadshotUpdated": null,
    "UsaTodayHeadshotNoBackgroundUpdated": null
  },
  {
    "PlayerId": 90116253,
    "FirstName": "Houssem",
    "LastName": "Tka",
    "CommonName": "Houssem Tka",
    "ShortName": "H. Tka",
    "Position": "M",
    "PositionCategory": "M",
    "Jersey": 8,
    "Foot": null,
    "Height": null,
    "Weight": null,
    "Gender": "Male",
    "BirthDate": "2000-08-16T00:00:00",
    "BirthCity": null,
    "BirthCountry": "Tunisia",
    "Nationality": "Tunisia",
    "InjuryStatus": "Scrambled",
    "InjuryBodyPart": "Scrambled",
    "InjuryNotes": "Scrambled",
    "InjuryStartDate": null,
    "Updated": "2025-06-16T19:53:23",
    "PhotoUrl": "https://s3-us-west-2.amazonaws.com/static.fantasydata.com/headshots/soc/low-res/0.png",
    "RotoWirePlayerID": null,
    "DraftKingsPosition": null,
    "UsaTodayPlayerID": null,
    "UsaTodayHeadshotUrl": null,
    "UsaTodayHeadshotNoBackgroundUrl": null,
    "UsaTodayHeadshotUpdated": null,
    "UsaTodayHeadshotNoBackgroundUpdated": null
  },
  {
    "PlayerId": 90116558,
    "FirstName": "Elias Sepho",
    "LastName": "Mokwana",
    "CommonName": "Elias Mokwana",
    "ShortName": "E. Mokwana",
    "Position": "A",
    "PositionCategory": "A",
    "Jersey": 24,
    "Foot": null,
    "Height": null,
    "Weight": null,
    "Gender": "Male",
    "BirthDate": "1999-09-08T00:00:00",
    "BirthCity": "KwaMhlanga",
    "BirthCountry": "South Africa",
    "Nationality": "South Africa",
    "InjuryStatus": "Scrambled",
    "InjuryBodyPart": "Scrambled",
    "InjuryNotes": "Scrambled",
    "InjuryStartDate": null,
    "Updated": "2025-06-16T19:53:23",
    "PhotoUrl": "https://s3-us-west-2.amazonaws.com/static.fantasydata.com/headshots/soc/low-res/0.png",
    "RotoWirePlayerID": null,
    "DraftKingsPosition": null,
    "UsaTodayPlayerID": null,
    "UsaTodayHeadshotUrl": null,
    "UsaTodayHeadshotNoBackgroundUrl": null,
    "UsaTodayHeadshotUpdated": null,
    "UsaTodayHeadshotNoBackgroundUpdated": null
  },
  {
    "PlayerId": 90119561,
    "FirstName": "Amenallah",
    "LastName": "Memmiche",
    "CommonName": "Amenallah Memmiche",
    "ShortName": "A. Memmiche",
    "Position": "GK",
    "PositionCategory": "GK",
    "Jersey": 1,
    "Foot": null,
    "Height": null,
    "Weight": null,
    "Gender": "Male",
    "BirthDate": "2004-04-20T00:00:00",
    "BirthCity": null,
    "BirthCountry": "Tunisia",
    "Nationality": "Tunisia",
    "InjuryStatus": "Scrambled",
    "InjuryBodyPart": "Scrambled",
    "InjuryNotes": "Scrambled",
    "InjuryStartDate": null,
    "Updated": "2025-06-16T19:53:23",
    "PhotoUrl": "https://s3-us-west-2.amazonaws.com/static.fantasydata.com/headshots/soc/low-res/0.png",
    "RotoWirePlayerID": null,
    "DraftKingsPosition": null,
    "UsaTodayPlayerID": null,
    "UsaTodayHeadshotUrl": null,
    "UsaTodayHeadshotNoBackgroundUrl": null,
    "UsaTodayHeadshotUpdated": null,
    "UsaTodayHeadshotNoBackgroundUpdated": null
  },
  {
    "PlayerId": 90124242,
    "FirstName": "Raed",
    "LastName": "Bouchniba",
    "CommonName": "Raed Bouchniba",
    "ShortName": "R. Bouchniba",
    "Position": "D",
    "PositionCategory": "D",
    "Jersey": 13,
    "Foot": null,
    "Height": null,
    "Weight": null,
    "Gender": "Male",
    "BirthDate": "2003-09-25T00:00:00",
    "BirthCity": null,
    "BirthCountry": "Tunisia",
    "Nationality": "Tunisia",
    "InjuryStatus": "Scrambled",
    "InjuryBodyPart": "Scrambled",
    "InjuryNotes": "Scrambled",
    "InjuryStartDate": null,
    "Updated": "2025-06-16T19:53:23",
    "PhotoUrl": "https://s3-us-west-2.amazonaws.com/static.fantasydata.com/headshots/soc/low-res/0.png",
    "RotoWirePlayerID": null,
    "DraftKingsPosition": null,
    "UsaTodayPlayerID": null,
    "UsaTodayHeadshotUrl": null,
    "UsaTodayHeadshotNoBackgroundUrl": null,
    "UsaTodayHeadshotUpdated": null,
    "UsaTodayHeadshotNoBackgroundUpdated": null
  },
  {
    "PlayerId": 90125526,
    "FirstName": "Chiheb",
    "LastName": "Jebali",
    "CommonName": "Chiheb Jebali",
    "ShortName": "C. Jebali",
    "Position": "A",
    "PositionCategory": "A",
    "Jersey": 36,
    "Foot": "Left",
    "Height": 176,
    "Weight": null,
    "Gender": "Male",
    "BirthDate": "1996-05-26T00:00:00",
    "BirthCity": null,
    "BirthCountry": "Tunisia",
    "Nationality": "Tunisia",
    "InjuryStatus": "Scrambled",
    "InjuryBodyPart": "Scrambled",
    "InjuryNotes": "Scrambled",
    "InjuryStartDate": null,
    "Updated": "2025-06-16T19:53:23",
    "PhotoUrl": "https://s3-us-west-2.amazonaws.com/static.fantasydata.com/headshots/soc/low-res/0.png",
    "RotoWirePlayerID": null,
    "DraftKingsPosition": null,
    "UsaTodayPlayerID": null,
    "UsaTodayHeadshotUrl": null,
    "UsaTodayHeadshotNoBackgroundUrl": null,
    "UsaTodayHeadshotUpdated": null,
    "UsaTodayHeadshotNoBackgroundUpdated": null
  },
  {
    "PlayerId": 90132736,
    "FirstName": "Mohamed El Mokhtar",
    "LastName": "Ifaoui",
    "CommonName": "Mohamed El Mokhtar Ifaoui",
    "ShortName": "M. Ifaoui",
    "Position": "GK",
    "PositionCategory": "GK",
    "Jersey": null,
    "Foot": null,
    "Height": null,
    "Weight": null,
    "Gender": "Male",
    "BirthDate": "2003-03-02T00:00:00",
    "BirthCity": null,
    "BirthCountry": "Tunisia",
    "Nationality": "Tunisia",
    "InjuryStatus": "Scrambled",
    "InjuryBodyPart": "Scrambled",
    "InjuryNotes": "Scrambled",
    "InjuryStartDate": null,
    "Updated": "2025-06-15T00:14:52",
    "PhotoUrl": "https://s3-us-west-2.amazonaws.com/static.fantasydata.com/headshots/soc/low-res/0.png",
    "RotoWirePlayerID": null,
    "DraftKingsPosition": null,
    "UsaTodayPlayerID": null,
    "UsaTodayHeadshotUrl": null,
    "UsaTodayHeadshotNoBackgroundUrl": null,
    "UsaTodayHeadshotUpdated": null,
    "UsaTodayHeadshotNoBackgroundUpdated": null
  },
  {
    "PlayerId": 90132737,
    "FirstName": "Wassim",
    "LastName": "Karoui",
    "CommonName": "Wassim Karoui",
    "ShortName": "W. Karoui",
    "Position": "GK",
    "PositionCategory": "GK",
    "Jersey": null,
    "Foot": null,
    "Height": null,
    "Weight": null,
    "Gender": "Male",
    "BirthDate": "1997-01-07T00:00:00",
    "BirthCity": null,
    "BirthCountry": "Tunisia",
    "Nationality": "Tunisia",
    "InjuryStatus": "Scrambled",
    "InjuryBodyPart": "Scrambled",
    "InjuryNotes": "Scrambled",
    "InjuryStartDate": null,
    "Updated": "2025-06-14T14:07:26",
    "PhotoUrl": "https://s3-us-west-2.amazonaws.com/static.fantasydata.com/headshots/soc/low-res/0.png",
    "RotoWirePlayerID": null,
    "DraftKingsPosition": null,
    "UsaTodayPlayerID": null,
    "UsaTodayHeadshotUrl": null,
    "UsaTodayHeadshotNoBackgroundUrl": null,
    "UsaTodayHeadshotUpdated": null,
    "UsaTodayHeadshotNoBackgroundUpdated": null
  },
  {
    "PlayerId": 90132738,
    "FirstName": "Mohamed Aziz",
    "LastName": "Kodhai",
    "CommonName": "Mohamed Aziz Kodhai",
    "ShortName": "M. Kodhai",
    "Position": "D",
    "PositionCategory": "D",
    "Jersey": 35,
    "Foot": null,
    "Height": null,
    "Weight": null,
    "Gender": "Male",
    "BirthDate": "2004-08-07T00:00:00",
    "BirthCity": null,
    "BirthCountry": "Tunisia",
    "Nationality": "Tunisia",
    "InjuryStatus": "Scrambled",
    "InjuryBodyPart": "Scrambled",
    "InjuryNotes": "Scrambled",
    "InjuryStartDate": null,
    "Updated": "2025-06-21T12:30:53",
    "PhotoUrl": "https://s3-us-west-2.amazonaws.com/static.fantasydata.com/headshots/soc/low-res/0.png",
    "RotoWirePlayerID": null,
    "DraftKingsPosition": null,
    "UsaTodayPlayerID": null,
    "UsaTodayHeadshotUrl": null,
    "UsaTodayHeadshotNoBackgroundUrl": null,
    "UsaTodayHeadshotUpdated": null,
    "UsaTodayHeadshotNoBackgroundUpdated": null
  },
  {
    "PlayerId": 90132739,
    "FirstName": "Alaaeddine",
    "LastName": "Derbali",
    "CommonName": "Alaaeddine Derbali",
    "ShortName": "A. Derbali",
    "Position": "D",
    "PositionCategory": "D",
    "Jersey": null,
    "Foot": null,
    "Height": null,
    "Weight": null,
    "Gender": "Male",
    "BirthDate": "2005-05-19T00:00:00",
    "BirthCity": null,
    "BirthCountry": "Tunisia",
    "Nationality": "Tunisia",
    "InjuryStatus": "Scrambled",
    "InjuryBodyPart": "Scrambled",
    "InjuryNotes": "Scrambled",
    "InjuryStartDate": null,
    "Updated": "2025-05-01T12:49:56",
    "PhotoUrl": "https://s3-us-west-2.amazonaws.com/static.fantasydata.com/headshots/soc/low-res/0.png",
    "RotoWirePlayerID": null,
    "DraftKingsPosition": null,
    "UsaTodayPlayerID": null,
    "UsaTodayHeadshotUrl": null,
    "UsaTodayHeadshotNoBackgroundUrl": null,
    "UsaTodayHeadshotUpdated": null,
    "UsaTodayHeadshotNoBackgroundUpdated": null
  },
  {
    "PlayerId": 90132740,
    "FirstName": "Kosay",
    "LastName": "Smiri",
    "CommonName": "Kosay Smiri",
    "ShortName": "K. Smiri",
    "Position": "D",
    "PositionCategory": "D",
    "Jersey": null,
    "Foot": null,
    "Height": null,
    "Weight": null,
    "Gender": "Male",
    "BirthDate": "2004-07-17T00:00:00",
    "BirthCity": null,
    "BirthCountry": "Tunisia",
    "Nationality": "Tunisia",
    "InjuryStatus": "Scrambled",
    "InjuryBodyPart": "Scrambled",
    "InjuryNotes": "Scrambled",
    "InjuryStartDate": null,
    "Updated": "2025-06-14T18:41:31",
    "PhotoUrl": "https://s3-us-west-2.amazonaws.com/static.fantasydata.com/headshots/soc/low-res/0.png",
    "RotoWirePlayerID": null,
    "DraftKingsPosition": null,
    "UsaTodayPlayerID": null,
    "UsaTodayHeadshotUrl": null,
    "UsaTodayHeadshotNoBackgroundUrl": null,
    "UsaTodayHeadshotUpdated": null,
    "UsaTodayHeadshotNoBackgroundUpdated": null
  },
  {
    "PlayerId": 90132741,
    "FirstName": "Mohamed",
    "LastName": "Ben Ali",
    "CommonName": "Mohamed Ben Ali",
    "ShortName": "M. Ben Ali",
    "Position": "D",
    "PositionCategory": "D",
    "Jersey": 2,
    "Foot": null,
    "Height": null,
    "Weight": null,
    "Gender": "Male",
    "BirthDate": "1995-02-16T00:00:00",
    "BirthCity": null,
    "BirthCountry": "Tunisia",
    "Nationality": "Tunisia",
    "InjuryStatus": "Scrambled",
    "InjuryBodyPart": "Scrambled",
    "InjuryNotes": "Scrambled",
    "InjuryStartDate": null,
    "Updated": "2025-06-16T19:53:23",
    "PhotoUrl": "https://s3-us-west-2.amazonaws.com/static.fantasydata.com/headshots/soc/low-res/0.png",
    "RotoWirePlayerID": null,
    "DraftKingsPosition": null,
    "UsaTodayPlayerID": null,
    "UsaTodayHeadshotUrl": null,
    "UsaTodayHeadshotNoBackgroundUrl": null,
    "UsaTodayHeadshotUpdated": null,
    "UsaTodayHeadshotNoBackgroundUpdated": null
  },
  {
    "PlayerId": 90132742,
    "FirstName": "Haythem",
    "LastName": "Dhaou",
    "CommonName": "Haythem Dhaou",
    "ShortName": "H. Dhaou",
    "Position": "M",
    "PositionCategory": "M",
    "Jersey": 12,
    "Foot": null,
    "Height": null,
    "Weight": null,
    "Gender": "Male",
    "BirthDate": "2005-01-12T00:00:00",
    "BirthCity": null,
    "BirthCountry": "Tunisia",
    "Nationality": "Tunisia",
    "InjuryStatus": "Scrambled",
    "InjuryBodyPart": "Scrambled",
    "InjuryNotes": "Scrambled",
    "InjuryStartDate": null,
    "Updated": "2025-06-16T19:53:23",
    "PhotoUrl": "https://s3-us-west-2.amazonaws.com/static.fantasydata.com/headshots/soc/low-res/0.png",
    "RotoWirePlayerID": null,
    "DraftKingsPosition": null,
    "UsaTodayPlayerID": null,
    "UsaTodayHeadshotUrl": null,
    "UsaTodayHeadshotNoBackgroundUrl": null,
    "UsaTodayHeadshotUpdated": null,
    "UsaTodayHeadshotNoBackgroundUpdated": null
  },
  {
    "PlayerId": 90132743,
    "FirstName": "Mohamed Mohieddine",
    "LastName": "Aloui",
    "CommonName": "Mohamed Mohieddine Aloui",
    "ShortName": "M. Aloui",
    "Position": "M",
    "PositionCategory": "M",
    "Jersey": null,
    "Foot": null,
    "Height": null,
    "Weight": null,
    "Gender": "Male",
    "BirthDate": "2004-07-17T00:00:00",
    "BirthCity": null,
    "BirthCountry": "Tunisia",
    "Nationality": "Tunisia",
    "InjuryStatus": "Scrambled",
    "InjuryBodyPart": "Scrambled",
    "InjuryNotes": "Scrambled",
    "InjuryStartDate": null,
    "Updated": "2025-06-14T18:41:31",
    "PhotoUrl": "https://s3-us-west-2.amazonaws.com/static.fantasydata.com/headshots/soc/low-res/0.png",
    "RotoWirePlayerID": null,
    "DraftKingsPosition": null,
    "UsaTodayPlayerID": null,
    "UsaTodayHeadshotUrl": null,
    "UsaTodayHeadshotNoBackgroundUrl": null,
    "UsaTodayHeadshotUpdated": null,
    "UsaTodayHeadshotNoBackgroundUpdated": null
  },
  {
    "PlayerId": 90132744,
    "FirstName": "Wajdi",
    "LastName": "Issaoui",
    "CommonName": "Wajdi Issaoui",
    "ShortName": "W. Issaoui",
    "Position": "M",
    "PositionCategory": "M",
    "Jersey": null,
    "Foot": null,
    "Height": null,
    "Weight": null,
    "Gender": "Male",
    "BirthDate": "2005-01-08T00:00:00",
    "BirthCity": null,
    "BirthCountry": "Tunisia",
    "Nationality": "Tunisia",
    "InjuryStatus": "Scrambled",
    "InjuryBodyPart": "Scrambled",
    "InjuryNotes": "Scrambled",
    "InjuryStartDate": null,
    "Updated": "2025-06-14T14:07:23",
    "PhotoUrl": "https://s3-us-west-2.amazonaws.com/static.fantasydata.com/headshots/soc/low-res/0.png",
    "RotoWirePlayerID": null,
    "DraftKingsPosition": null,
    "UsaTodayPlayerID": null,
    "UsaTodayHeadshotUrl": null,
    "UsaTodayHeadshotNoBackgroundUrl": null,
    "UsaTodayHeadshotUpdated": null,
    "UsaTodayHeadshotNoBackgroundUpdated": null
  },
  {
    "PlayerId": 90132745,
    "FirstName": "Elyas",
    "LastName": "Bouzaiene",
    "CommonName": "Elyas Bouzaiene",
    "ShortName": "E. Bouzaiene",
    "Position": "M",
    "PositionCategory": "M",
    "Jersey": null,
    "Foot": null,
    "Height": null,
    "Weight": null,
    "Gender": "Male",
    "BirthDate": "1997-09-08T00:00:00",
    "BirthCity": null,
    "BirthCountry": "Sweden",
    "Nationality": "Sweden",
    "InjuryStatus": "Scrambled",
    "InjuryBodyPart": "Scrambled",
    "InjuryNotes": "Scrambled",
    "InjuryStartDate": null,
    "Updated": "2025-06-14T14:07:26",
    "PhotoUrl": "https://s3-us-west-2.amazonaws.com/static.fantasydata.com/headshots/soc/low-res/0.png",
    "RotoWirePlayerID": null,
    "DraftKingsPosition": null,
    "UsaTodayPlayerID": null,
    "UsaTodayHeadshotUrl": null,
    "UsaTodayHeadshotNoBackgroundUrl": null,
    "UsaTodayHeadshotUpdated": null,
    "UsaTodayHeadshotNoBackgroundUpdated": null
  },
  {
    "PlayerId": 90132746,
    "FirstName": "Khalil",
    "LastName": "Guenichi",
    "CommonName": "Khalil Guenichi",
    "ShortName": "K. Guenichi",
    "Position": "M",
    "PositionCategory": "M",
    "Jersey": 38,
    "Foot": null,
    "Height": null,
    "Weight": null,
    "Gender": "Male",
    "BirthDate": "2002-12-11T00:00:00",
    "BirthCity": null,
    "BirthCountry": "Tunisia",
    "Nationality": "Tunisia",
    "InjuryStatus": "Scrambled",
    "InjuryBodyPart": "Scrambled",
    "InjuryNotes": "Scrambled",
    "InjuryStartDate": null,
    "Updated": "2025-06-16T19:53:23",
    "PhotoUrl": "https://s3-us-west-2.amazonaws.com/static.fantasydata.com/headshots/soc/low-res/0.png",
    "RotoWirePlayerID": null,
    "DraftKingsPosition": null,
    "UsaTodayPlayerID": null,
    "UsaTodayHeadshotUrl": null,
    "UsaTodayHeadshotNoBackgroundUrl": null,
    "UsaTodayHeadshotUpdated": null,
    "UsaTodayHeadshotNoBackgroundUpdated": null
  },
  {
    "PlayerId": 90132747,
    "FirstName": "Zakaria",
    "LastName": "El Ayeb",
    "CommonName": "Zakaria El Ayeb",
    "ShortName": "Z. El Ayeb",
    "Position": "M",
    "PositionCategory": "M",
    "Jersey": null,
    "Foot": null,
    "Height": null,
    "Weight": null,
    "Gender": "Male",
    "BirthDate": "2003-01-15T00:00:00",
    "BirthCity": null,
    "BirthCountry": "Tunisia",
    "Nationality": "Tunisia",
    "InjuryStatus": "Scrambled",
    "InjuryBodyPart": "Scrambled",
    "InjuryNotes": "Scrambled",
    "InjuryStartDate": null,
    "Updated": "2025-06-14T14:07:26",
    "PhotoUrl": "https://s3-us-west-2.amazonaws.com/static.fantasydata.com/headshots/soc/low-res/0.png",
    "RotoWirePlayerID": null,
    "DraftKingsPosition": null,
    "UsaTodayPlayerID": null,
    "UsaTodayHeadshotUrl": null,
    "UsaTodayHeadshotNoBackgroundUrl": null,
    "UsaTodayHeadshotUpdated": null,
    "UsaTodayHeadshotNoBackgroundUpdated": null
  },
  {
    "PlayerId": 90132748,
    "FirstName": "Onuche",
    "LastName": "Ogbelu",
    "CommonName": "Onuche Ogbelu",
    "ShortName": "O. Ogbelu",
    "Position": "M",
    "PositionCategory": "M",
    "Jersey": 14,
    "Foot": null,
    "Height": null,
    "Weight": null,
    "Gender": "Male",
    "BirthDate": "2003-05-10T00:00:00",
    "BirthCity": null,
    "BirthCountry": "Nigeria",
    "Nationality": "Nigeria",
    "InjuryStatus": "Scrambled",
    "InjuryBodyPart": "Scrambled",
    "InjuryNotes": "Scrambled",
    "InjuryStartDate": null,
    "Updated": "2025-06-16T19:53:23",
    "PhotoUrl": "https://s3-us-west-2.amazonaws.com/static.fantasydata.com/headshots/soc/low-res/0.png",
    "RotoWirePlayerID": null,
    "DraftKingsPosition": null,
    "UsaTodayPlayerID": null,
    "UsaTodayHeadshotUrl": null,
    "UsaTodayHeadshotNoBackgroundUrl": null,
    "UsaTodayHeadshotUpdated": null,
    "UsaTodayHeadshotNoBackgroundUpdated": null
  },
  {
    "PlayerId": 90132749,
    "FirstName": "Aboubacar",
    "LastName": "Diakité",
    "CommonName": "Aboubacar Diakité",
    "ShortName": "A. Diakité",
    "Position": "M",
    "PositionCategory": "M",
    "Jersey": null,
    "Foot": null,
    "Height": null,
    "Weight": null,
    "Gender": "Male",
    "BirthDate": "2006-12-31T00:00:00",
    "BirthCity": null,
    "BirthCountry": "Mali",
    "Nationality": "Mali",
    "InjuryStatus": "Scrambled",
    "InjuryBodyPart": "Scrambled",
    "InjuryNotes": "Scrambled",
    "InjuryStartDate": null,
    "Updated": "2025-06-21T12:30:53",
    "PhotoUrl": "https://s3-us-west-2.amazonaws.com/static.fantasydata.com/headshots/soc/low-res/0.png",
    "RotoWirePlayerID": null,
    "DraftKingsPosition": null,
    "UsaTodayPlayerID": null,
    "UsaTodayHeadshotUrl": null,
    "UsaTodayHeadshotNoBackgroundUrl": null,
    "UsaTodayHeadshotUpdated": null,
    "UsaTodayHeadshotNoBackgroundUpdated": null
  },
  {
    "PlayerId": 90132750,
    "FirstName": "Mohamed",
    "LastName": "Mouhli",
    "CommonName": "Midou Mouhli",
    "ShortName": "M. Mouhli",
    "Position": "A",
    "PositionCategory": "A",
    "Jersey": null,
    "Foot": null,
    "Height": 179,
    "Weight": 77,
    "Gender": "Male",
    "BirthDate": "1998-09-13T00:00:00",
    "BirthCity": null,
    "BirthCountry": "Belgium",
    "Nationality": "Belgium",
    "InjuryStatus": "Scrambled",
    "InjuryBodyPart": "Scrambled",
    "InjuryNotes": "Scrambled",
    "InjuryStartDate": null,
    "Updated": "2025-06-14T18:41:31",
    "PhotoUrl": "https://s3-us-west-2.amazonaws.com/static.fantasydata.com/headshots/soc/low-res/0.png",
    "RotoWirePlayerID": null,
    "DraftKingsPosition": null,
    "UsaTodayPlayerID": null,
    "UsaTodayHeadshotUrl": null,
    "UsaTodayHeadshotNoBackgroundUrl": null,
    "UsaTodayHeadshotUpdated": null,
    "UsaTodayHeadshotNoBackgroundUpdated": null
  },
  {
    "PlayerId": 90132751,
    "FirstName": "Mohamed Rayane",
    "LastName": "Hamrouni",
    "CommonName": "Mohamed Rayane Hamrouni",
    "ShortName": "M. Hamrouni",
    "Position": "A",
    "PositionCategory": "A",
    "Jersey": 39,
    "Foot": null,
    "Height": null,
    "Weight": null,
    "Gender": "Male",
    "BirthDate": "2003-01-29T00:00:00",
    "BirthCity": null,
    "BirthCountry": "Tunisia",
    "Nationality": "Tunisia",
    "InjuryStatus": "Scrambled",
    "InjuryBodyPart": "Scrambled",
    "InjuryNotes": "Scrambled",
    "InjuryStartDate": null,
    "Updated": "2025-06-21T12:30:53",
    "PhotoUrl": "https://s3-us-west-2.amazonaws.com/static.fantasydata.com/headshots/soc/low-res/0.png",
    "RotoWirePlayerID": null,
    "DraftKingsPosition": null,
    "UsaTodayPlayerID": null,
    "UsaTodayHeadshotUrl": null,
    "UsaTodayHeadshotNoBackgroundUrl": null,
    "UsaTodayHeadshotUpdated": null,
    "UsaTodayHeadshotNoBackgroundUpdated": null
  },
  {
    "PlayerId": 90132752,
    "FirstName": "Achref",
    "LastName": "Jebri",
    "CommonName": "Achref Jebri",
    "ShortName": "A. Jebri",
    "Position": "A",
    "PositionCategory": "A",
    "Jersey": 19,
    "Foot": null,
    "Height": null,
    "Weight": null,
    "Gender": "Male",
    "BirthDate": "2001-12-26T00:00:00",
    "BirthCity": null,
    "BirthCountry": "Tunisia",
    "Nationality": "Tunisia",
    "InjuryStatus": "Scrambled",
    "InjuryBodyPart": "Scrambled",
    "InjuryNotes": "Scrambled",
    "InjuryStartDate": null,
    "Updated": "2025-06-16T19:53:23",
    "PhotoUrl": "https://s3-us-west-2.amazonaws.com/static.fantasydata.com/headshots/soc/low-res/0.png",
    "RotoWirePlayerID": null,
    "DraftKingsPosition": null,
    "UsaTodayPlayerID": null,
    "UsaTodayHeadshotUrl": null,
    "UsaTodayHeadshotNoBackgroundUrl": null,
    "UsaTodayHeadshotUpdated": null,
    "UsaTodayHeadshotNoBackgroundUpdated": null
  },
  {
    "PlayerId": 90132753,
    "FirstName": "Amenallah",
    "LastName": "Frikhi",
    "CommonName": "Amenallah Frikhi",
    "ShortName": "A. Frikhi",
    "Position": "A",
    "PositionCategory": "A",
    "Jersey": null,
    "Foot": null,
    "Height": null,
    "Weight": null,
    "Gender": "Male",
    "BirthDate": "2004-02-12T00:00:00",
    "BirthCity": null,
    "BirthCountry": "Tunisia",
    "Nationality": "Tunisia",
    "InjuryStatus": "Scrambled",
    "InjuryBodyPart": "Scrambled",
    "InjuryNotes": "Scrambled",
    "InjuryStartDate": null,
    "Updated": "2025-06-14T18:41:31",
    "PhotoUrl": "https://s3-us-west-2.amazonaws.com/static.fantasydata.com/headshots/soc/low-res/0.png",
    "RotoWirePlayerID": null,
    "DraftKingsPosition": null,
    "UsaTodayPlayerID": null,
    "UsaTodayHeadshotUrl": null,
    "UsaTodayHeadshotNoBackgroundUrl": null,
    "UsaTodayHeadshotUpdated": null,
    "UsaTodayHeadshotNoBackgroundUpdated": null
  },
  {
    "PlayerId": 90132754,
    "FirstName": "Koussay",
    "LastName": "Ben Maacha",
    "CommonName": "Koussay Ben Maacha",
    "ShortName": "K. Ben Maacha",
    "Position": "A",
    "PositionCategory": "A",
    "Jersey": null,
    "Foot": null,
    "Height": null,
    "Weight": null,
    "Gender": "Male",
    "BirthDate": "2007-05-21T00:00:00",
    "BirthCity": null,
    "BirthCountry": "Tunisia",
    "Nationality": "Tunisia",
    "InjuryStatus": "Scrambled",
    "InjuryBodyPart": "Scrambled",
    "InjuryNotes": "Scrambled",
    "InjuryStartDate": null,
    "Updated": "2025-06-14T18:41:31",
    "PhotoUrl": "https://s3-us-west-2.amazonaws.com/static.fantasydata.com/headshots/soc/low-res/0.png",
    "RotoWirePlayerID": null,
    "DraftKingsPosition": null,
    "UsaTodayPlayerID": null,
    "UsaTodayHeadshotUrl": null,
    "UsaTodayHeadshotNoBackgroundUrl": null,
    "UsaTodayHeadshotUpdated": null,
    "UsaTodayHeadshotNoBackgroundUpdated": null
  },
  {
    "PlayerId": 90132755,
    "FirstName": "Raed",
    "LastName": "El Fadee",
    "CommonName": "Raed El Fadee",
    "ShortName": "R. El Fadee",
    "Position": "A",
    "PositionCategory": "A",
    "Jersey": null,
    "Foot": null,
    "Height": null,
    "Weight": null,
    "Gender": "Male",
    "BirthDate": "1997-05-20T00:00:00",
    "BirthCity": null,
    "BirthCountry": "Tunisia",
    "Nationality": "Tunisia",
    "InjuryStatus": "Scrambled",
    "InjuryBodyPart": "Scrambled",
    "InjuryNotes": "Scrambled",
    "InjuryStartDate": null,
    "Updated": "2025-06-14T18:41:31",
    "PhotoUrl": "https://s3-us-west-2.amazonaws.com/static.fantasydata.com/headshots/soc/low-res/0.png",
    "RotoWirePlayerID": null,
    "DraftKingsPosition": null,
    "UsaTodayPlayerID": null,
    "UsaTodayHeadshotUrl": null,
    "UsaTodayHeadshotNoBackgroundUrl": null,
    "UsaTodayHeadshotUpdated": null,
    "UsaTodayHeadshotNoBackgroundUpdated": null
  },
  {
    "PlayerId": 90132756,
    "FirstName": "Zineddine",
    "LastName": "Kada",
    "CommonName": "Zineddine Kada",
    "ShortName": "Z. Kada",
    "Position": "A",
    "PositionCategory": "A",
    "Jersey": null,
    "Foot": null,
    "Height": null,
    "Weight": null,
    "Gender": "Male",
    "BirthDate": "2005-08-01T00:00:00",
    "BirthCity": null,
    "BirthCountry": "Tunisia",
    "Nationality": "Tunisia",
    "InjuryStatus": "Scrambled",
    "InjuryBodyPart": "Scrambled",
    "InjuryNotes": "Scrambled",
    "InjuryStartDate": null,
    "Updated": "2025-06-14T18:41:31",
    "PhotoUrl": "https://s3-us-west-2.amazonaws.com/static.fantasydata.com/headshots/soc/low-res/0.png",
    "RotoWirePlayerID": null,
    "DraftKingsPosition": null,
    "UsaTodayPlayerID": null,
    "UsaTodayHeadshotUrl": null,
    "UsaTodayHeadshotNoBackgroundUrl": null,
    "UsaTodayHeadshotUpdated": null,
    "UsaTodayHeadshotNoBackgroundUpdated": null
  },
  {
    "PlayerId": 90132757,
    "FirstName": "Bilel",
    "LastName": "Sahli",
    "CommonName": "Bilel Sahli",
    "ShortName": "B. Sahli",
    "Position": "A",
    "PositionCategory": "A",
    "Jersey": null,
    "Foot": null,
    "Height": null,
    "Weight": null,
    "Gender": "Male",
    "BirthDate": "2003-04-16T00:00:00",
    "BirthCity": null,
    "BirthCountry": "France",
    "Nationality": "France",
    "InjuryStatus": "Scrambled",
    "InjuryBodyPart": "Scrambled",
    "InjuryNotes": "Scrambled",
    "InjuryStartDate": null,
    "Updated": "2025-06-14T14:07:26",
    "PhotoUrl": "https://s3-us-west-2.amazonaws.com/static.fantasydata.com/headshots/soc/low-res/0.png",
    "RotoWirePlayerID": null,
    "DraftKingsPosition": null,
    "UsaTodayPlayerID": null,
    "UsaTodayHeadshotUrl": null,
    "UsaTodayHeadshotNoBackgroundUrl": null,
    "UsaTodayHeadshotUpdated": null,
    "UsaTodayHeadshotNoBackgroundUpdated": null
  }
]