[
  {
    "PlayerId": 90026854,
    "FirstName": "Stefan",
    "LastName": "Bell",
    "CommonName": "Stefan Bell",
    "ShortName": "S. Bell",
    "Position": "D",
    "PositionCategory": "D",
    "Jersey": 16,
    "Foot": "Right",
    "Height": 192,
    "Weight": 86,
    "Gender": "Male",
    "BirthDate": "1991-08-24T00:00:00",
    "BirthCity": "Andernach, Rheinland-Pfalz",
    "BirthCountry": "Germany",
    "Nationality": "Germany",
    "InjuryStatus": "Scrambled",
    "InjuryBodyPart": "Scrambled",
    "InjuryNotes": "Scrambled",
    "InjuryStartDate": null,
    "Updated": "2025-07-04T01:19:14",
    "PhotoUrl": "https://s3-us-west-2.amazonaws.com/static.fantasydata.com/headshots/soc/low-res/90026854.png",
    "RotoWirePlayerID": null,
    "DraftKingsPosition": "D",
    "UsaTodayPlayerID": null,
    "UsaTodayHeadshotUrl": null,
    "UsaTodayHeadshotNoBackgroundUrl": null,
    "UsaTodayHeadshotUpdated": null,
    "UsaTodayHeadshotNoBackgroundUpdated": null
  },
  {
    "PlayerId": 90027023,
    "FirstName": "Dominik",
    "LastName": "Kohr",
    "CommonName": "Dominik Kohr",
    "ShortName": "D. Kohr",
    "Position": "M",
    "PositionCategory": "M",
    "Jersey": 31,
    "Foot": "Left",
    "Height": 183,
    "Weight": 75,
    "Gender": "Male",
    "BirthDate": "1994-01-31T00:00:00",
    "BirthCity": "Trier",
    "BirthCountry": "Germany",
    "Nationality": "Germany",
    "InjuryStatus": "Scrambled",
    "InjuryBodyPart": "Scrambled",
    "InjuryNotes": "Scrambled",
    "InjuryStartDate": "2025-05-04T00:00:00",
    "Updated": "2025-07-05T05:39:12",
    "PhotoUrl": "https://s3-us-west-2.amazonaws.com/static.fantasydata.com/headshots/soc/low-res/90027023.png",
    "RotoWirePlayerID": null,
    "DraftKingsPosition": "M",
    "UsaTodayPlayerID": null,
    "UsaTodayHeadshotUrl": null,
    "UsaTodayHeadshotNoBackgroundUrl": null,
    "UsaTodayHeadshotUpdated": null,
    "UsaTodayHeadshotNoBackgroundUpdated": null
  },
  {
    "PlayerId": 90027083,
    "FirstName": "Danny",
    "LastName": "Vieira da Costa",
    "CommonName": "Danny da Costa",
    "ShortName": "D. da Costa",
    "Position": "D",
    "PositionCategory": "D",
    "Jersey": 21,
    "Foot": "Right",
    "Height": 185,
    "Weight": 81,
    "Gender": "Male",
    "BirthDate": "1993-07-13T00:00:00",
    "BirthCity": "Neuss",
    "BirthCountry": "Germany",
    "Nationality": "Germany",
    "InjuryStatus": "Scrambled",
    "InjuryBodyPart": "Scrambled",
    "InjuryNotes": "Scrambled",
    "InjuryStartDate": null,
    "Updated": "2025-07-04T01:26:15",
    "PhotoUrl": "https://s3-us-west-2.amazonaws.com/static.fantasydata.com/headshots/soc/low-res/90027083.png",
    "RotoWirePlayerID": null,
    "DraftKingsPosition": "D",
    "UsaTodayPlayerID": null,
    "UsaTodayHeadshotUrl": null,
    "UsaTodayHeadshotNoBackgroundUrl": null,
    "UsaTodayHeadshotUpdated": null,
    "UsaTodayHeadshotNoBackgroundUpdated": null
  },
  {
    "PlayerId": 90027309,
    "FirstName": "Nadiem",
    "LastName": "Amiri",
    "CommonName": "Nadiem Amiri",
    "ShortName": "N. Amiri",
    "Position": "M",
    "PositionCategory": "M",
    "Jersey": 18,
    "Foot": "Right",
    "Height": 180,
    "Weight": 70,
    "Gender": "Male",
    "BirthDate": "1996-10-27T00:00:00",
    "BirthCity": "Ludwigshafen",
    "BirthCountry": "Germany",
    "Nationality": "Germany",
    "InjuryStatus": "Scrambled",
    "InjuryBodyPart": "Scrambled",
    "InjuryNotes": "Scrambled",
    "InjuryStartDate": null,
    "Updated": "2025-07-04T01:33:08",
    "PhotoUrl": "https://s3-us-west-2.amazonaws.com/static.fantasydata.com/headshots/soc/low-res/90027309.png",
    "RotoWirePlayerID": 19623,
    "DraftKingsPosition": "M",
    "UsaTodayPlayerID": null,
    "UsaTodayHeadshotUrl": null,
    "UsaTodayHeadshotNoBackgroundUrl": null,
    "UsaTodayHeadshotUpdated": null,
    "UsaTodayHeadshotNoBackgroundUpdated": null
  },
  {
    "PlayerId": 90031408,
    "FirstName": "Silvan",
    "LastName": "Widmer",
    "CommonName": "Silvan Widmer",
    "ShortName": "S. Widmer",
    "Position": "D",
    "PositionCategory": "D",
    "Jersey": 30,
    "Foot": "Right",
    "Height": 182,
    "Weight": 79,
    "Gender": "Male",
    "BirthDate": "1993-03-05T00:00:00",
    "BirthCity": "Spreitenbach",
    "BirthCountry": "Switzerland",
    "Nationality": "Switzerland",
    "InjuryStatus": "Scrambled",
    "InjuryBodyPart": "Scrambled",
    "InjuryNotes": "Scrambled",
    "InjuryStartDate": null,
    "Updated": "2025-07-04T03:05:35",
    "PhotoUrl": "https://s3-us-west-2.amazonaws.com/static.fantasydata.com/headshots/soc/low-res/90031408.png",
    "RotoWirePlayerID": 20801,
    "DraftKingsPosition": "D",
    "UsaTodayPlayerID": null,
    "UsaTodayHeadshotUrl": null,
    "UsaTodayHeadshotNoBackgroundUrl": null,
    "UsaTodayHeadshotUpdated": null,
    "UsaTodayHeadshotNoBackgroundUpdated": null
  },
  {
    "PlayerId": 90033749,
    "FirstName": "Edimilson",
    "LastName": "Fernandes",
    "CommonName": "Edimilson Fernandes",
    "ShortName": "Edimilson Fernandes",
    "Position": "M",
    "PositionCategory": "M",
    "Jersey": 6,
    "Foot": "Right",
    "Height": 190,
    "Weight": 70,
    "Gender": "Male",
    "BirthDate": "1996-04-15T00:00:00",
    "BirthCity": "Sion",
    "BirthCountry": "Switzerland",
    "Nationality": "Switzerland",
    "InjuryStatus": "Scrambled",
    "InjuryBodyPart": "Scrambled",
    "InjuryNotes": "Scrambled",
    "InjuryStartDate": null,
    "Updated": "2025-07-04T03:57:02",
    "PhotoUrl": "https://s3-us-west-2.amazonaws.com/static.fantasydata.com/headshots/soc/low-res/90033749.png",
    "RotoWirePlayerID": 23191,
    "DraftKingsPosition": "M",
    "UsaTodayPlayerID": null,
    "UsaTodayHeadshotUrl": null,
    "UsaTodayHeadshotNoBackgroundUrl": null,
    "UsaTodayHeadshotUpdated": null,
    "UsaTodayHeadshotNoBackgroundUpdated": null
  },
  {
    "PlayerId": 90042835,
    "FirstName": "Andreas",
    "LastName": "Schjølberg Hanche-Olsen",
    "CommonName": "Andreas Hanche-Olsen",
    "ShortName": "A. Hanche-Olsen",
    "Position": "D",
    "PositionCategory": "D",
    "Jersey": 25,
    "Foot": "Right",
    "Height": 185,
    "Weight": 82,
    "Gender": "Male",
    "BirthDate": "1997-01-17T00:00:00",
    "BirthCity": "Bodø",
    "BirthCountry": "Norway",
    "Nationality": "Norway",
    "InjuryStatus": "Scrambled",
    "InjuryBodyPart": "Scrambled",
    "InjuryNotes": "Scrambled",
    "InjuryStartDate": null,
    "Updated": "2025-07-04T06:51:23",
    "PhotoUrl": "https://s3-us-west-2.amazonaws.com/static.fantasydata.com/headshots/soc/low-res/90042835.png",
    "RotoWirePlayerID": null,
    "DraftKingsPosition": "D",
    "UsaTodayPlayerID": null,
    "UsaTodayHeadshotUrl": null,
    "UsaTodayHeadshotNoBackgroundUrl": null,
    "UsaTodayHeadshotUpdated": null,
    "UsaTodayHeadshotNoBackgroundUpdated": null
  },
  {
    "PlayerId": 90044766,
    "FirstName": "Arnaud",
    "LastName": "Nordin",
    "CommonName": "Arnaud Nordin",
    "ShortName": "A. Nordin",
    "Position": "M",
    "PositionCategory": "M",
    "Jersey": 9,
    "Foot": "Right",
    "Height": 178,
    "Weight": 70,
    "Gender": "Male",
    "BirthDate": "1998-06-17T00:00:00",
    "BirthCity": "Saint-Étienne",
    "BirthCountry": "France",
    "Nationality": "France",
    "InjuryStatus": "Scrambled",
    "InjuryBodyPart": "Scrambled",
    "InjuryNotes": "Scrambled",
    "InjuryStartDate": null,
    "Updated": "2025-07-04T07:27:36",
    "PhotoUrl": "https://s3-us-west-2.amazonaws.com/static.fantasydata.com/headshots/soc/low-res/90044766.png",
    "RotoWirePlayerID": null,
    "DraftKingsPosition": "M/F",
    "UsaTodayPlayerID": null,
    "UsaTodayHeadshotUrl": null,
    "UsaTodayHeadshotNoBackgroundUrl": null,
    "UsaTodayHeadshotUpdated": null,
    "UsaTodayHeadshotNoBackgroundUpdated": null
  },
  {
    "PlayerId": 90048760,
    "FirstName": "Anthony",
    "LastName": "Caci",
    "CommonName": "Anthony Caci",
    "ShortName": "A. Caci",
    "Position": "D",
    "PositionCategory": "D",
    "Jersey": 19,
    "Foot": "Right",
    "Height": 184,
    "Weight": 70,
    "Gender": "Male",
    "BirthDate": "1997-07-01T00:00:00",
    "BirthCity": "Forbach",
    "BirthCountry": "France",
    "Nationality": "France",
    "InjuryStatus": "Scrambled",
    "InjuryBodyPart": "Scrambled",
    "InjuryNotes": "Scrambled",
    "InjuryStartDate": null,
    "Updated": "2025-07-04T08:32:35",
    "PhotoUrl": "https://s3-us-west-2.amazonaws.com/static.fantasydata.com/headshots/soc/low-res/90048760.png",
    "RotoWirePlayerID": null,
    "DraftKingsPosition": "D",
    "UsaTodayPlayerID": null,
    "UsaTodayHeadshotUrl": null,
    "UsaTodayHeadshotNoBackgroundUrl": null,
    "UsaTodayHeadshotUpdated": null,
    "UsaTodayHeadshotNoBackgroundUpdated": null
  },
  {
    "PlayerId": 90050971,
    "FirstName": "Robin",
    "LastName": "Zentner",
    "CommonName": "Robin Zentner",
    "ShortName": "R. Zentner",
    "Position": "GK",
    "PositionCategory": "GK",
    "Jersey": 27,
    "Foot": "Right",
    "Height": 194,
    "Weight": 96,
    "Gender": "Male",
    "BirthDate": "1994-10-28T00:00:00",
    "BirthCity": "Ludwigshafen am Rhein",
    "BirthCountry": "Germany",
    "Nationality": "Germany",
    "InjuryStatus": "Scrambled",
    "InjuryBodyPart": "Scrambled",
    "InjuryNotes": "Scrambled",
    "InjuryStartDate": null,
    "Updated": "2025-06-30T08:54:05",
    "PhotoUrl": "https://s3-us-west-2.amazonaws.com/static.fantasydata.com/headshots/soc/low-res/90050971.png",
    "RotoWirePlayerID": null,
    "DraftKingsPosition": "GK",
    "UsaTodayPlayerID": null,
    "UsaTodayHeadshotUrl": null,
    "UsaTodayHeadshotNoBackgroundUrl": null,
    "UsaTodayHeadshotUpdated": null,
    "UsaTodayHeadshotNoBackgroundUpdated": null
  },
  {
    "PlayerId": 90053297,
    "FirstName": "Jaesung",
    "LastName": "Lee",
    "CommonName": "Lee Jaesung",
    "ShortName": "Lee Jaesung",
    "Position": "M",
    "PositionCategory": "M",
    "Jersey": 7,
    "Foot": "Left",
    "Height": 180,
    "Weight": 70,
    "Gender": "Male",
    "BirthDate": "1992-08-10T00:00:00",
    "BirthCity": "Ulsan",
    "BirthCountry": "Korea Republic",
    "Nationality": "Korea Republic",
    "InjuryStatus": "Scrambled",
    "InjuryBodyPart": "Scrambled",
    "InjuryNotes": "Scrambled",
    "InjuryStartDate": null,
    "Updated": "2024-07-22T08:58:08",
    "PhotoUrl": "https://s3-us-west-2.amazonaws.com/static.fantasydata.com/headshots/soc/low-res/90053297.png",
    "RotoWirePlayerID": null,
    "DraftKingsPosition": "M",
    "UsaTodayPlayerID": null,
    "UsaTodayHeadshotUrl": null,
    "UsaTodayHeadshotNoBackgroundUrl": null,
    "UsaTodayHeadshotUpdated": null,
    "UsaTodayHeadshotNoBackgroundUpdated": null
  },
  {
    "PlayerId": 90066334,
    "FirstName": "Philipp",
    "LastName": "Mwene",
    "CommonName": "Philipp Mwene",
    "ShortName": "P. Mwene",
    "Position": "D",
    "PositionCategory": "D",
    "Jersey": 2,
    "Foot": "Right",
    "Height": 170,
    "Weight": 68,
    "Gender": "Male",
    "BirthDate": "1994-01-29T00:00:00",
    "BirthCity": "Wien",
    "BirthCountry": "Austria",
    "Nationality": "Austria",
    "InjuryStatus": "Scrambled",
    "InjuryBodyPart": "Scrambled",
    "InjuryNotes": "Scrambled",
    "InjuryStartDate": null,
    "Updated": "2025-04-27T13:12:37",
    "PhotoUrl": "https://s3-us-west-2.amazonaws.com/static.fantasydata.com/headshots/soc/low-res/90066334.png",
    "RotoWirePlayerID": null,
    "DraftKingsPosition": "D",
    "UsaTodayPlayerID": null,
    "UsaTodayHeadshotUrl": null,
    "UsaTodayHeadshotNoBackgroundUrl": null,
    "UsaTodayHeadshotUpdated": null,
    "UsaTodayHeadshotNoBackgroundUpdated": null
  },
  {
    "PlayerId": 90071031,
    "FirstName": "Tom",
    "LastName": "Krauß",
    "CommonName": "Tom Krauß",
    "ShortName": "T. Krauß",
    "Position": "M",
    "PositionCategory": "M",
    "Jersey": 17,
    "Foot": "Right",
    "Height": 182,
    "Weight": 72,
    "Gender": "Male",
    "BirthDate": "2001-06-22T00:00:00",
    "BirthCity": "Leipzig",
    "BirthCountry": "Germany",
    "Nationality": "Germany",
    "InjuryStatus": "Scrambled",
    "InjuryBodyPart": "Scrambled",
    "InjuryNotes": "Scrambled",
    "InjuryStartDate": "2025-05-15T00:00:00",
    "Updated": "2025-07-05T05:39:12",
    "PhotoUrl": "https://s3-us-west-2.amazonaws.com/static.fantasydata.com/headshots/soc/low-res/90071031.png",
    "RotoWirePlayerID": null,
    "DraftKingsPosition": "M",
    "UsaTodayPlayerID": null,
    "UsaTodayHeadshotUrl": null,
    "UsaTodayHeadshotNoBackgroundUrl": null,
    "UsaTodayHeadshotUpdated": null,
    "UsaTodayHeadshotNoBackgroundUpdated": null
  },
  {
    "PlayerId": 90074455,
    "FirstName": "Lennard",
    "LastName": "Maloney",
    "CommonName": "Lennard Maloney",
    "ShortName": "L. Maloney",
    "Position": "M",
    "PositionCategory": "M",
    "Jersey": 15,
    "Foot": "Right",
    "Height": 187,
    "Weight": 84,
    "Gender": "Male",
    "BirthDate": "1999-10-08T00:00:00",
    "BirthCity": "Berlin, Berlin",
    "BirthCountry": "Germany",
    "Nationality": "United States",
    "InjuryStatus": "Scrambled",
    "InjuryBodyPart": "Scrambled",
    "InjuryNotes": "Scrambled",
    "InjuryStartDate": null,
    "Updated": "2025-01-25T08:42:58",
    "PhotoUrl": "https://s3-us-west-2.amazonaws.com/static.fantasydata.com/headshots/soc/low-res/90074455.png",
    "RotoWirePlayerID": null,
    "DraftKingsPosition": "M",
    "UsaTodayPlayerID": null,
    "UsaTodayHeadshotUrl": null,
    "UsaTodayHeadshotNoBackgroundUrl": null,
    "UsaTodayHeadshotUpdated": null,
    "UsaTodayHeadshotNoBackgroundUpdated": null
  },
  {
    "PlayerId": 90089190,
    "FirstName": "Paul",
    "LastName": "Nebel",
    "CommonName": "Paul Nebel",
    "ShortName": "P. Nebel",
    "Position": "A",
    "PositionCategory": "A",
    "Jersey": 8,
    "Foot": "Both",
    "Height": 169,
    "Weight": 63,
    "Gender": "Male",
    "BirthDate": "2002-10-10T00:00:00",
    "BirthCity": "Frankfurt am Main",
    "BirthCountry": "Germany",
    "Nationality": "Germany",
    "InjuryStatus": "Scrambled",
    "InjuryBodyPart": "Scrambled",
    "InjuryNotes": "Scrambled",
    "InjuryStartDate": null,
    "Updated": "2024-08-24T08:34:16",
    "PhotoUrl": "https://s3-us-west-2.amazonaws.com/static.fantasydata.com/headshots/soc/low-res/90089190.png",
    "RotoWirePlayerID": null,
    "DraftKingsPosition": "M",
    "UsaTodayPlayerID": null,
    "UsaTodayHeadshotUrl": null,
    "UsaTodayHeadshotNoBackgroundUrl": null,
    "UsaTodayHeadshotUpdated": null,
    "UsaTodayHeadshotNoBackgroundUpdated": null
  },
  {
    "PlayerId": 90090358,
    "FirstName": "Armindo",
    "LastName": "Sieb",
    "CommonName": "Armindo Sieb",
    "ShortName": "A. Sieb",
    "Position": "A",
    "PositionCategory": "A",
    "Jersey": 11,
    "Foot": "Both",
    "Height": 180,
    "Weight": 72,
    "Gender": "Male",
    "BirthDate": "2003-02-17T00:00:00",
    "BirthCity": "Halle (Saale)",
    "BirthCountry": "Germany",
    "Nationality": "Germany",
    "InjuryStatus": "Scrambled",
    "InjuryBodyPart": "Scrambled",
    "InjuryNotes": "Scrambled",
    "InjuryStartDate": null,
    "Updated": "2024-08-24T08:34:16",
    "PhotoUrl": "https://s3-us-west-2.amazonaws.com/static.fantasydata.com/headshots/soc/low-res/90090358.png",
    "RotoWirePlayerID": null,
    "DraftKingsPosition": "F",
    "UsaTodayPlayerID": null,
    "UsaTodayHeadshotUrl": null,
    "UsaTodayHeadshotNoBackgroundUrl": null,
    "UsaTodayHeadshotUpdated": null,
    "UsaTodayHeadshotNoBackgroundUpdated": null
  },
  {
    "PlayerId": 90096548,
    "FirstName": "Maxim",
    "LastName": "Leitsch",
    "CommonName": "Maxim Leitsch",
    "ShortName": "M. Leitsch",
    "Position": "D",
    "PositionCategory": "D",
    "Jersey": 5,
    "Foot": "Left",
    "Height": 187,
    "Weight": 80,
    "Gender": "Male",
    "BirthDate": "1998-05-18T00:00:00",
    "BirthCity": "Essen",
    "BirthCountry": "Germany",
    "Nationality": "Germany",
    "InjuryStatus": "Scrambled",
    "InjuryBodyPart": "Scrambled",
    "InjuryNotes": "Scrambled",
    "InjuryStartDate": null,
    "Updated": "2025-05-02T11:06:40",
    "PhotoUrl": "https://s3-us-west-2.amazonaws.com/static.fantasydata.com/headshots/soc/low-res/90096548.png",
    "RotoWirePlayerID": null,
    "DraftKingsPosition": "D",
    "UsaTodayPlayerID": null,
    "UsaTodayHeadshotUrl": null,
    "UsaTodayHeadshotNoBackgroundUrl": null,
    "UsaTodayHeadshotUpdated": null,
    "UsaTodayHeadshotNoBackgroundUpdated": null
  },
  {
    "PlayerId": 90098122,
    "FirstName": "Ben Justus",
    "LastName": "Bobzien",
    "CommonName": "Ben Bobzien",
    "ShortName": "B. Bobzien",
    "Position": "A",
    "PositionCategory": "A",
    "Jersey": 38,
    "Foot": null,
    "Height": null,
    "Weight": null,
    "Gender": "Male",
    "BirthDate": "2003-04-29T00:00:00",
    "BirthCity": null,
    "BirthCountry": "Germany",
    "Nationality": "Germany",
    "InjuryStatus": "Scrambled",
    "InjuryBodyPart": "Scrambled",
    "InjuryNotes": "Scrambled",
    "InjuryStartDate": null,
    "Updated": "2025-07-02T10:11:54",
    "PhotoUrl": "https://s3-us-west-2.amazonaws.com/static.fantasydata.com/headshots/soc/low-res/90098122.png",
    "RotoWirePlayerID": null,
    "DraftKingsPosition": "F",
    "UsaTodayPlayerID": null,
    "UsaTodayHeadshotUrl": null,
    "UsaTodayHeadshotNoBackgroundUrl": null,
    "UsaTodayHeadshotUpdated": null,
    "UsaTodayHeadshotNoBackgroundUpdated": null
  },
  {
    "PlayerId": 90102209,
    "FirstName": "Lasse Finn",
    "LastName": "Rieß",
    "CommonName": "Lasse Rieß",
    "ShortName": "L. Rieß",
    "Position": "GK",
    "PositionCategory": "GK",
    "Jersey": 1,
    "Foot": null,
    "Height": null,
    "Weight": null,
    "Gender": "Male",
    "BirthDate": "2001-07-27T00:00:00",
    "BirthCity": null,
    "BirthCountry": "Germany",
    "Nationality": "Germany",
    "InjuryStatus": "Scrambled",
    "InjuryBodyPart": "Scrambled",
    "InjuryNotes": "Scrambled",
    "InjuryStartDate": null,
    "Updated": "2023-08-26T12:01:21",
    "PhotoUrl": "https://s3-us-west-2.amazonaws.com/static.fantasydata.com/headshots/soc/low-res/90102209.png",
    "RotoWirePlayerID": null,
    "DraftKingsPosition": null,
    "UsaTodayPlayerID": null,
    "UsaTodayHeadshotUrl": null,
    "UsaTodayHeadshotNoBackgroundUrl": null,
    "UsaTodayHeadshotUpdated": null,
    "UsaTodayHeadshotNoBackgroundUpdated": null
  },
  {
    "PlayerId": 90106647,
    "FirstName": "Nelson Felix Patrick",
    "LastName": "Weiper",
    "CommonName": "Nelson Weiper",
    "ShortName": "N. Weiper",
    "Position": "A",
    "PositionCategory": "A",
    "Jersey": 44,
    "Foot": null,
    "Height": null,
    "Weight": null,
    "Gender": "Male",
    "BirthDate": "2005-03-17T00:00:00",
    "BirthCity": null,
    "BirthCountry": "Germany",
    "Nationality": "Germany",
    "InjuryStatus": "Scrambled",
    "InjuryBodyPart": "Scrambled",
    "InjuryNotes": "Scrambled",
    "InjuryStartDate": null,
    "Updated": "2025-06-12T14:15:28",
    "PhotoUrl": "https://s3-us-west-2.amazonaws.com/static.fantasydata.com/headshots/soc/low-res/0.png",
    "RotoWirePlayerID": null,
    "DraftKingsPosition": "F",
    "UsaTodayPlayerID": null,
    "UsaTodayHeadshotUrl": null,
    "UsaTodayHeadshotNoBackgroundUrl": null,
    "UsaTodayHeadshotUpdated": null,
    "UsaTodayHeadshotNoBackgroundUpdated": null
  },
  {
    "PlayerId": 90111570,
    "FirstName": "Hyunseok",
    "LastName": "Hong",
    "CommonName": "Hong Hyunseok",
    "ShortName": "Hong Hyunseok",
    "Position": "M",
    "PositionCategory": "M",
    "Jersey": 14,
    "Foot": "Left",
    "Height": 177,
    "Weight": 68,
    "Gender": "Male",
    "BirthDate": "1999-06-16T00:00:00",
    "BirthCity": "Seoul",
    "BirthCountry": "Korea Republic",
    "Nationality": "Korea Republic",
    "InjuryStatus": "Scrambled",
    "InjuryBodyPart": "Scrambled",
    "InjuryNotes": "Scrambled",
    "InjuryStartDate": null,
    "Updated": "2025-03-15T06:38:17",
    "PhotoUrl": "https://s3-us-west-2.amazonaws.com/static.fantasydata.com/headshots/soc/low-res/0.png",
    "RotoWirePlayerID": null,
    "DraftKingsPosition": null,
    "UsaTodayPlayerID": null,
    "UsaTodayHeadshotUrl": null,
    "UsaTodayHeadshotNoBackgroundUrl": null,
    "UsaTodayHeadshotUpdated": null,
    "UsaTodayHeadshotNoBackgroundUpdated": null
  },
  {
    "PlayerId": 90111811,
    "FirstName": "Daniel",
    "LastName": "Batz",
    "CommonName": "Daniel Batz",
    "ShortName": "D. Batz",
    "Position": "GK",
    "PositionCategory": "GK",
    "Jersey": 33,
    "Foot": "Right",
    "Height": 189,
    "Weight": 84,
    "Gender": "Male",
    "BirthDate": "1991-01-12T00:00:00",
    "BirthCity": "Erlangen",
    "BirthCountry": "Germany",
    "Nationality": "Germany",
    "InjuryStatus": "Scrambled",
    "InjuryBodyPart": "Scrambled",
    "InjuryNotes": "Scrambled",
    "InjuryStartDate": null,
    "Updated": "2023-09-02T09:31:28",
    "PhotoUrl": "https://s3-us-west-2.amazonaws.com/static.fantasydata.com/headshots/soc/low-res/0.png",
    "RotoWirePlayerID": null,
    "DraftKingsPosition": null,
    "UsaTodayPlayerID": null,
    "UsaTodayHeadshotUrl": null,
    "UsaTodayHeadshotNoBackgroundUrl": null,
    "UsaTodayHeadshotUpdated": null,
    "UsaTodayHeadshotNoBackgroundUpdated": null
  },
  {
    "PlayerId": 90112434,
    "FirstName": "Benedict",
    "LastName": "Hollerbach",
    "CommonName": "Benedict Hollerbach",
    "ShortName": "B. Hollerbach",
    "Position": "A",
    "PositionCategory": "A",
    "Jersey": 16,
    "Foot": null,
    "Height": null,
    "Weight": null,
    "Gender": "Male",
    "BirthDate": "2001-05-17T00:00:00",
    "BirthCity": null,
    "BirthCountry": "Germany",
    "Nationality": "Germany",
    "InjuryStatus": "Scrambled",
    "InjuryBodyPart": "Scrambled",
    "InjuryNotes": "Scrambled",
    "InjuryStartDate": null,
    "Updated": "2025-06-04T04:35:36",
    "PhotoUrl": "https://s3-us-west-2.amazonaws.com/static.fantasydata.com/headshots/soc/low-res/0.png",
    "RotoWirePlayerID": null,
    "DraftKingsPosition": "F",
    "UsaTodayPlayerID": null,
    "UsaTodayHeadshotUrl": null,
    "UsaTodayHeadshotNoBackgroundUrl": null,
    "UsaTodayHeadshotUpdated": null,
    "UsaTodayHeadshotNoBackgroundUpdated": null
  },
  {
    "PlayerId": 90116516,
    "FirstName": "Kaishu",
    "LastName": "Sano",
    "CommonName": "Kaishu Sano",
    "ShortName": "K. Sano",
    "Position": "M",
    "PositionCategory": "M",
    "Jersey": 6,
    "Foot": null,
    "Height": 176,
    "Weight": 67,
    "Gender": "Male",
    "BirthDate": "2000-12-30T00:00:00",
    "BirthCity": null,
    "BirthCountry": "Japan",
    "Nationality": "Japan",
    "InjuryStatus": "Scrambled",
    "InjuryBodyPart": "Scrambled",
    "InjuryNotes": "Scrambled",
    "InjuryStartDate": null,
    "Updated": "2025-06-02T06:19:48",
    "PhotoUrl": "https://s3-us-west-2.amazonaws.com/static.fantasydata.com/headshots/soc/low-res/0.png",
    "RotoWirePlayerID": null,
    "DraftKingsPosition": null,
    "UsaTodayPlayerID": null,
    "UsaTodayHeadshotUrl": null,
    "UsaTodayHeadshotNoBackgroundUrl": null,
    "UsaTodayHeadshotUpdated": null,
    "UsaTodayHeadshotNoBackgroundUpdated": null
  },
  {
    "PlayerId": 90118662,
    "FirstName": "Kasey Willem",
    "LastName": "Bos",
    "CommonName": "Kasey Bos",
    "ShortName": "K. Bos",
    "Position": "D",
    "PositionCategory": "D",
    "Jersey": 28,
    "Foot": null,
    "Height": null,
    "Weight": null,
    "Gender": "Male",
    "BirthDate": "2004-05-08T00:00:00",
    "BirthCity": "Werribee, VIC",
    "BirthCountry": "Australia",
    "Nationality": "Australia",
    "InjuryStatus": "Scrambled",
    "InjuryBodyPart": "Scrambled",
    "InjuryNotes": "Scrambled",
    "InjuryStartDate": null,
    "Updated": "2025-07-02T10:11:54",
    "PhotoUrl": "https://s3-us-west-2.amazonaws.com/static.fantasydata.com/headshots/soc/low-res/0.png",
    "RotoWirePlayerID": null,
    "DraftKingsPosition": null,
    "UsaTodayPlayerID": null,
    "UsaTodayHeadshotUrl": null,
    "UsaTodayHeadshotNoBackgroundUrl": null,
    "UsaTodayHeadshotUpdated": null,
    "UsaTodayHeadshotNoBackgroundUpdated": null
  },
  {
    "PlayerId": 90118717,
    "FirstName": "Maxim Bora",
    "LastName": "Dal",
    "CommonName": "Maxim Dal",
    "ShortName": "M. Dal",
    "Position": "D",
    "PositionCategory": "D",
    "Jersey": 34,
    "Foot": null,
    "Height": 188,
    "Weight": null,
    "Gender": "Male",
    "BirthDate": "2006-01-26T00:00:00",
    "BirthCity": null,
    "BirthCountry": "Germany",
    "Nationality": "Germany",
    "InjuryStatus": "Scrambled",
    "InjuryBodyPart": "Scrambled",
    "InjuryNotes": "Scrambled",
    "InjuryStartDate": "2025-05-08T00:00:00",
    "Updated": "2025-07-05T05:39:12",
    "PhotoUrl": "https://s3-us-west-2.amazonaws.com/static.fantasydata.com/headshots/soc/low-res/0.png",
    "RotoWirePlayerID": null,
    "DraftKingsPosition": null,
    "UsaTodayPlayerID": null,
    "UsaTodayHeadshotUrl": null,
    "UsaTodayHeadshotNoBackgroundUrl": null,
    "UsaTodayHeadshotUpdated": null,
    "UsaTodayHeadshotNoBackgroundUpdated": null
  },
  {
    "PlayerId": 90122197,
    "FirstName": "Nikolas Konrad",
    "LastName": "Veratschnig",
    "CommonName": "Nikolas Veratschnig",
    "ShortName": "N. Veratschnig",
    "Position": "M",
    "PositionCategory": "M",
    "Jersey": 22,
    "Foot": null,
    "Height": null,
    "Weight": null,
    "Gender": "Male",
    "BirthDate": "2003-01-24T00:00:00",
    "BirthCity": null,
    "BirthCountry": "Austria",
    "Nationality": "Austria",
    "InjuryStatus": "Scrambled",
    "InjuryBodyPart": "Scrambled",
    "InjuryNotes": "Scrambled",
    "InjuryStartDate": null,
    "Updated": "2025-06-06T09:06:58",
    "PhotoUrl": "https://s3-us-west-2.amazonaws.com/static.fantasydata.com/headshots/soc/low-res/0.png",
    "RotoWirePlayerID": null,
    "DraftKingsPosition": null,
    "UsaTodayPlayerID": null,
    "UsaTodayHeadshotUrl": null,
    "UsaTodayHeadshotNoBackgroundUrl": null,
    "UsaTodayHeadshotUpdated": null,
    "UsaTodayHeadshotNoBackgroundUpdated": null
  },
  {
    "PlayerId": 90125314,
    "FirstName": "Daniel",
    "LastName": "Gleiber",
    "CommonName": "Daniel Gleiber",
    "ShortName": "D. Gleiber",
    "Position": "M",
    "PositionCategory": "M",
    "Jersey": 42,
    "Foot": null,
    "Height": null,
    "Weight": null,
    "Gender": "Male",
    "BirthDate": "2005-02-01T00:00:00",
    "BirthCity": null,
    "BirthCountry": "Germany",
    "Nationality": "Germany",
    "InjuryStatus": "Scrambled",
    "InjuryBodyPart": "Scrambled",
    "InjuryNotes": "Scrambled",
    "InjuryStartDate": null,
    "Updated": "2024-09-28T09:31:52",
    "PhotoUrl": "https://s3-us-west-2.amazonaws.com/static.fantasydata.com/headshots/soc/low-res/0.png",
    "RotoWirePlayerID": null,
    "DraftKingsPosition": null,
    "UsaTodayPlayerID": null,
    "UsaTodayHeadshotUrl": null,
    "UsaTodayHeadshotNoBackgroundUrl": null,
    "UsaTodayHeadshotUpdated": null,
    "UsaTodayHeadshotNoBackgroundUpdated": null
  },
  {
    "PlayerId": 90125459,
    "FirstName": "Konstantin",
    "LastName": "Schopp",
    "CommonName": "Konstantin Schopp",
    "ShortName": "K. Schopp",
    "Position": "D",
    "PositionCategory": "D",
    "Jersey": 32,
    "Foot": null,
    "Height": null,
    "Weight": null,
    "Gender": "Male",
    "BirthDate": "2005-12-30T00:00:00",
    "BirthCity": null,
    "BirthCountry": "Austria",
    "Nationality": "Austria",
    "InjuryStatus": "Scrambled",
    "InjuryBodyPart": "Scrambled",
    "InjuryNotes": "Scrambled",
    "InjuryStartDate": null,
    "Updated": "2025-07-01T05:10:09",
    "PhotoUrl": "https://s3-us-west-2.amazonaws.com/static.fantasydata.com/headshots/soc/low-res/0.png",
    "RotoWirePlayerID": null,
    "DraftKingsPosition": null,
    "UsaTodayPlayerID": null,
    "UsaTodayHeadshotUrl": null,
    "UsaTodayHeadshotNoBackgroundUrl": null,
    "UsaTodayHeadshotUpdated": null,
    "UsaTodayHeadshotNoBackgroundUpdated": null
  },
  {
    "PlayerId": 90133628,
    "FirstName": "Mikkel",
    "LastName": "Jespersen",
    "CommonName": "Mikkel Jespersen",
    "ShortName": "M. Jespersen",
    "Position": "M",
    "PositionCategory": "M",
    "Jersey": null,
    "Foot": null,
    "Height": null,
    "Weight": null,
    "Gender": "Male",
    "BirthDate": "1991-06-11T00:00:00",
    "BirthCity": null,
    "BirthCountry": "Denmark",
    "Nationality": "Denmark",
    "InjuryStatus": "Scrambled",
    "InjuryBodyPart": "Scrambled",
    "InjuryNotes": "Scrambled",
    "InjuryStartDate": null,
    "Updated": "2025-06-06T05:31:20",
    "PhotoUrl": "https://s3-us-west-2.amazonaws.com/static.fantasydata.com/headshots/soc/low-res/0.png",
    "RotoWirePlayerID": null,
    "DraftKingsPosition": null,
    "UsaTodayPlayerID": null,
    "UsaTodayHeadshotUrl": null,
    "UsaTodayHeadshotNoBackgroundUrl": null,
    "UsaTodayHeadshotUpdated": null,
    "UsaTodayHeadshotNoBackgroundUpdated": null
  }
]